[{"TimeUTC":"2025-11-06 16:18:59","timestampInMs":1762445939985,"requestPath":"server-mcdcs-gzqa0kxnj-yeshwant-raos-projects.vercel.app/","requestMethod":"GET","requestQueryString":"","responseStatusCode":-1,"requestId":"wltnz-1762445938107-8ea22e901b0c","requestUserAgent":"vercel-screenshot/1.0","level":"error","environment":"production","branch":"main","vercelCache":"","type":"lambda","function":"/server.js","host":"server-mcdcs-gzqa0kxnj-yeshwant-raos-projects.vercel.app","deploymentDomain":"server-mcdcs-gzqa0kxnj-yeshwant-raos-projects.vercel.app","deploymentId":"dpl_BtemsWCTW2zp1MqxH6gCzwKfbXau","durationMs":-1,"region":"iad1","maxMemoryUsed":-1,"memorySize":-1,"message":"Error: ENOENT: no such file or directory, stat '/var/task/frontend/dist/index.html'","projectId":"prj_uRMIndd7p1kBQ5otSkgRpD3RLMnU","traceId":"","sessionId":"","invocationId":"01K9CZDKNS5AFPNT5WT93ME2F1","instanceId":"","concurrency":-1},{"TimeUTC":"2025-11-06 16:18:59","timestampInMs":1762445939941,"requestPath":"server-mcdcs-gzqa0kxnj-yeshwant-raos-projects.vercel.app/","requestMethod":"GET","requestQueryString":"","responseStatusCode":-1,"requestId":"wltnz-1762445938107-8ea22e901b0c","requestUserAgent":"vercel-screenshot/1.0","level":"info","environment":"production","branch":"main","vercelCache":"","type":"lambda","function":"/server.js","host":"server-mcdcs-gzqa0kxnj-yeshwant-raos-projects.vercel.app","deploymentDomain":"server-mcdcs-gzqa0kxnj-yeshwant-raos-projects.vercel.app","deploymentId":"dpl_BtemsWCTW2zp1MqxH6gCzwKfbXau","durationMs":-1,"region":"iad1","maxMemoryUsed":-1,"memorySize":-1,"message":"(node:4) [MONGODB DRIVER] Warning: useUnifiedTopology is a deprecated option: useUnifiedTopology has no effect since Node.js Driver version 4.0.0 and will be removed in the next major version","projectId":"prj_uRMIndd7p1kBQ5otSkgRpD3RLMnU","traceId":"","sessionId":"","invocationId":"01K9CZDKNS5AFPNT5WT93ME2F1","instanceId":"","concurrency":-1},{"TimeUTC":"2025-11-06 16:18:59","timestampInMs":1762445939941,"requestPath":"server-mcdcs-gzqa0kxnj-yeshwant-raos-projects.vercel.app/","requestMethod":"GET","requestQueryString":"","responseStatusCode":-1,"requestId":"wltnz-1762445938107-8ea22e901b0c","requestUserAgent":"vercel-screenshot/1.0","level":"info","environment":"production","branch":"main","vercelCache":"","type":"lambda","function":"/server.js","host":"server-mcdcs-gzqa0kxnj-yeshwant-raos-projects.vercel.app","deploymentDomain":"server-mcdcs-gzqa0kxnj-yeshwant-raos-projects.vercel.app","deploymentId":"dpl_BtemsWCTW2zp1MqxH6gCzwKfbXau","durationMs":-1,"region":"iad1","maxMemoryUsed":-1,"memorySize":-1,"message":"(node:4) [MONGODB DRIVER] Warning: useNewUrlParser is a deprecated option: useNewUrlParser has no effect since Node.js Driver version 4.0.0 and will be removed in the next major version\r(Use `node --trace-warnings ...` to show where the warning was created)","projectId":"prj_uRMIndd7p1kBQ5otSkgRpD3RLMnU","traceId":"","sessionId":"","invocationId":"01K9CZDKNS5AFPNT5WT93ME2F1","instanceId":"","concurrency":-1},{"TimeUTC":"2025-11-06 16:18:59","timestampInMs":1762445939941,"requestPath":"server-mcdcs-gzqa0kxnj-yeshwant-raos-projects.vercel.app/","requestMethod":"GET","requestQueryString":"","responseStatusCode":-1,"requestId":"wltnz-1762445938107-8ea22e901b0c","requestUserAgent":"vercel-screenshot/1.0","level":"info","environment":"production","branch":"main","vercelCache":"","type":"lambda","function":"/server.js","host":"server-mcdcs-gzqa0kxnj-yeshwant-raos-projects.vercel.app","deploymentDomain":"server-mcdcs-gzqa0kxnj-yeshwant-raos-projects.vercel.app","deploymentId":"dpl_BtemsWCTW2zp1MqxH6gCzwKfbXau","durationMs":-1,"region":"iad1","maxMemoryUsed":-1,"memorySize":-1,"message":"[dotenv@17.2.2] injecting env (0) from .env -- tip: ⚙️  enable debug logging with { debug: true }","projectId":"prj_uRMIndd7p1kBQ5otSkgRpD3RLMnU","traceId":"","sessionId":"","invocationId":"01K9CZDKNS5AFPNT5WT93ME2F1","instanceId":"","concurrency":-1},{"TimeUTC":"2025-11-06 16:18:59","timestampInMs":1762445939050,"requestPath":"server-mcdcs-gzqa0kxnj-yeshwant-raos-projects.vercel.app/favicon.ico","requestMethod":"GET","requestQueryString":"","responseStatusCode":-1,"requestId":"bnzkw-1762445938883-6231b03ad1d2","requestUserAgent":"vercel-screenshot/1.0","level":"error","environment":"production","branch":"main","vercelCache":"","type":"lambda","function":"/server.js","host":"server-mcdcs-gzqa0kxnj-yeshwant-raos-projects.vercel.app","deploymentDomain":"server-mcdcs-gzqa0kxnj-yeshwant-raos-projects.vercel.app","deploymentId":"dpl_BtemsWCTW2zp1MqxH6gCzwKfbXau","durationMs":-1,"region":"iad1","maxMemoryUsed":-1,"memorySize":-1,"message":"Error: ENOENT: no such file or directory, stat '/var/task/frontend/dist/index.html'","projectId":"prj_uRMIndd7p1kBQ5otSkgRpD3RLMnU","traceId":"","sessionId":"","invocationId":"01K9CZDMAD2PYBRBT9CBT4EGY5","instanceId":"","concurrency":-1},{"TimeUTC":"2025-11-06 16:18:59","timestampInMs":1762445939021,"requestPath":"server-mcdcs-gzqa0kxnj-yeshwant-raos-projects.vercel.app/favicon.ico","requestMethod":"GET","requestQueryString":"","responseStatusCode":404,"requestId":"bnzkw-1762445938883-6231b03ad1d2","requestUserAgent":"vercel-screenshot/1.0","level":"warning","environment":"production","branch":"main","vercelCache":"","type":"lambda","function":"/server.js","host":"server-mcdcs-gzqa0kxnj-yeshwant-raos-projects.vercel.app","deploymentDomain":"server-mcdcs-gzqa0kxnj-yeshwant-raos-projects.vercel.app","deploymentId":"dpl_BtemsWCTW2zp1MqxH6gCzwKfbXau","durationMs":19,"region":"iad1","maxMemoryUsed":212,"memorySize":2048,"message":"","projectId":"prj_uRMIndd7p1kBQ5otSkgRpD3RLMnU","traceId":"","sessionId":"","invocationId":"01K9CZDMAD2PYBRBT9CBT4EGY5","instanceId":"uADiTowSXNaq","concurrency":1},{"TimeUTC":"2025-11-06 16:18:58","timestampInMs":1762445938725,"requestPath":"server-mcdcs-gzqa0kxnj-yeshwant-raos-projects.vercel.app/","requestMethod":"GET","requestQueryString":"","responseStatusCode":-1,"requestId":"x2bh2-1762445938526-110b8f2b6f70","requestUserAgent":"vercel-screenshot/1.0","level":"error","environment":"production","branch":"main","vercelCache":"","type":"lambda","function":"/server.js","host":"server-mcdcs-gzqa0kxnj-yeshwant-raos-projects.vercel.app","deploymentDomain":"server-mcdcs-gzqa0kxnj-yeshwant-raos-projects.vercel.app","deploymentId":"dpl_BtemsWCTW2zp1MqxH6gCzwKfbXau","durationMs":-1,"region":"iad1","maxMemoryUsed":-1,"memorySize":-1,"message":"Error: ENOENT: no such file or directory, stat '/var/task/frontend/dist/index.html'","projectId":"prj_uRMIndd7p1kBQ5otSkgRpD3RLMnU","traceId":"","sessionId":"","invocationId":"01K9CZDKZKF5TJR9V6KPQV0908","instanceId":"","concurrency":-1},{"TimeUTC":"2025-11-06 16:18:58","timestampInMs":1762445938675,"requestPath":"server-mcdcs-gzqa0kxnj-yeshwant-raos-projects.vercel.app/","requestMethod":"GET","requestQueryString":"","responseStatusCode":404,"requestId":"x2bh2-1762445938526-110b8f2b6f70","requestUserAgent":"vercel-screenshot/1.0","level":"warning","environment":"production","branch":"main","vercelCache":"","type":"lambda","function":"/server.js","host":"server-mcdcs-gzqa0kxnj-yeshwant-raos-projects.vercel.app","deploymentDomain":"server-mcdcs-gzqa0kxnj-yeshwant-raos-projects.vercel.app","deploymentId":"dpl_BtemsWCTW2zp1MqxH6gCzwKfbXau","durationMs":39,"region":"iad1","maxMemoryUsed":212,"memorySize":2048,"message":"","projectId":"prj_uRMIndd7p1kBQ5otSkgRpD3RLMnU","traceId":"","sessionId":"","invocationId":"01K9CZDKZKF5TJR9V6KPQV0908","instanceId":"uADiTowSXNaq","concurrency":1},{"TimeUTC":"2025-11-06 16:18:58","timestampInMs":1762445938630,"requestPath":"server-mcdcs-gzqa0kxnj-yeshwant-raos-projects.vercel.app/","requestMethod":"GET","requestQueryString":"","responseStatusCode":-1,"requestId":"lqfjn-1762445938093-9efc43ef3b47","requestUserAgent":"vercel-screenshot/1.0","level":"error","environment":"production","branch":"main","vercelCache":"","type":"lambda","function":"/server.js","host":"server-mcdcs-gzqa0kxnj-yeshwant-raos-projects.vercel.app","deploymentDomain":"server-mcdcs-gzqa0kxnj-yeshwant-raos-projects.vercel.app","deploymentId":"dpl_BtemsWCTW2zp1MqxH6gCzwKfbXau","durationMs":-1,"region":"iad1","maxMemoryUsed":-1,"memorySize":-1,"message":"Error: ENOENT: no such file or directory, stat '/var/task/frontend/dist/index.html'","projectId":"prj_uRMIndd7p1kBQ5otSkgRpD3RLMnU","traceId":"","sessionId":"","invocationId":"01K9CZDKNNJ42Z6Q82YHJX52G1","instanceId":"","concurrency":-1},{"TimeUTC":"2025-11-06 16:18:58","timestampInMs":1762445938380,"requestPath":"server-mcdcs-gzqa0kxnj-yeshwant-raos-projects.vercel.app/","requestMethod":"GET","requestQueryString":"","responseStatusCode":-1,"requestId":"lqfjn-1762445938093-9efc43ef3b47","requestUserAgent":"vercel-screenshot/1.0","level":"info","environment":"production","branch":"main","vercelCache":"","type":"lambda","function":"/server.js","host":"server-mcdcs-gzqa0kxnj-yeshwant-raos-projects.vercel.app","deploymentDomain":"server-mcdcs-gzqa0kxnj-yeshwant-raos-projects.vercel.app","deploymentId":"dpl_BtemsWCTW2zp1MqxH6gCzwKfbXau","durationMs":-1,"region":"iad1","maxMemoryUsed":-1,"memorySize":-1,"message":"(node:4) [MONGODB DRIVER] Warning: useUnifiedTopology is a deprecated option: useUnifiedTopology has no effect since Node.js Driver version 4.0.0 and will be removed in the next major version","projectId":"prj_uRMIndd7p1kBQ5otSkgRpD3RLMnU","traceId":"","sessionId":"","invocationId":"01K9CZDKNNJ42Z6Q82YHJX52G1","instanceId":"","concurrency":-1},{"TimeUTC":"2025-11-06 16:18:58","timestampInMs":1762445938380,"requestPath":"server-mcdcs-gzqa0kxnj-yeshwant-raos-projects.vercel.app/","requestMethod":"GET","requestQueryString":"","responseStatusCode":-1,"requestId":"lqfjn-1762445938093-9efc43ef3b47","requestUserAgent":"vercel-screenshot/1.0","level":"info","environment":"production","branch":"main","vercelCache":"","type":"lambda","function":"/server.js","host":"server-mcdcs-gzqa0kxnj-yeshwant-raos-projects.vercel.app","deploymentDomain":"server-mcdcs-gzqa0kxnj-yeshwant-raos-projects.vercel.app","deploymentId":"dpl_BtemsWCTW2zp1MqxH6gCzwKfbXau","durationMs":-1,"region":"iad1","maxMemoryUsed":-1,"memorySize":-1,"message":"(node:4) [MONGODB DRIVER] Warning: useNewUrlParser is a deprecated option: useNewUrlParser has no effect since Node.js Driver version 4.0.0 and will be removed in the next major version\r(Use `node --trace-warnings ...` to show where the warning was created)","projectId":"prj_uRMIndd7p1kBQ5otSkgRpD3RLMnU","traceId":"","sessionId":"","invocationId":"01K9CZDKNNJ42Z6Q82YHJX52G1","instanceId":"","concurrency":-1},{"TimeUTC":"2025-11-06 16:18:58","timestampInMs":1762445938380,"requestPath":"server-mcdcs-gzqa0kxnj-yeshwant-raos-projects.vercel.app/","requestMethod":"GET","requestQueryString":"","responseStatusCode":-1,"requestId":"lqfjn-1762445938093-9efc43ef3b47","requestUserAgent":"vercel-screenshot/1.0","level":"info","environment":"production","branch":"main","vercelCache":"","type":"lambda","function":"/server.js","host":"server-mcdcs-gzqa0kxnj-yeshwant-raos-projects.vercel.app","deploymentDomain":"server-mcdcs-gzqa0kxnj-yeshwant-raos-projects.vercel.app","deploymentId":"dpl_BtemsWCTW2zp1MqxH6gCzwKfbXau","durationMs":-1,"region":"iad1","maxMemoryUsed":-1,"memorySize":-1,"message":"[dotenv@17.2.2] injecting env (0) from .env -- tip: 📡 version env with Radar: https://dotenvx.com/radar","projectId":"prj_uRMIndd7p1kBQ5otSkgRpD3RLMnU","traceId":"","sessionId":"","invocationId":"01K9CZDKNNJ42Z6Q82YHJX52G1","instanceId":"","concurrency":-1},{"TimeUTC":"2025-11-06 16:18:58","timestampInMs":1762445938361,"requestPath":"server-mcdcs-gzqa0kxnj-yeshwant-raos-projects.vercel.app/","requestMethod":"GET","requestQueryString":"","responseStatusCode":404,"requestId":"wltnz-1762445938107-8ea22e901b0c","requestUserAgent":"vercel-screenshot/1.0","level":"warning","environment":"production","branch":"main","vercelCache":"","type":"lambda","function":"/server.js","host":"server-mcdcs-gzqa0kxnj-yeshwant-raos-projects.vercel.app","deploymentDomain":"server-mcdcs-gzqa0kxnj-yeshwant-raos-projects.vercel.app","deploymentId":"dpl_BtemsWCTW2zp1MqxH6gCzwKfbXau","durationMs":1427,"region":"iad1","maxMemoryUsed":164,"memorySize":2048,"message":"","projectId":"prj_uRMIndd7p1kBQ5otSkgRpD3RLMnU","traceId":"","sessionId":"","invocationId":"01K9CZDKNS5AFPNT5WT93ME2F1","instanceId":"BJWCO2rJJsey","concurrency":1},{"TimeUTC":"2025-11-06 16:18:58","timestampInMs":1762445938357,"requestPath":"server-mcdcs-gzqa0kxnj-yeshwant-raos-projects.vercel.app/","requestMethod":"GET","requestQueryString":"","responseStatusCode":404,"requestId":"lqfjn-1762445938093-9efc43ef3b47","requestUserAgent":"vercel-screenshot/1.0","level":"warning","environment":"production","branch":"main","vercelCache":"","type":"lambda","function":"/server.js","host":"server-mcdcs-gzqa0kxnj-yeshwant-raos-projects.vercel.app","deploymentDomain":"server-mcdcs-gzqa0kxnj-yeshwant-raos-projects.vercel.app","deploymentId":"dpl_BtemsWCTW2zp1MqxH6gCzwKfbXau","durationMs":266,"region":"iad1","maxMemoryUsed":212,"memorySize":2048,"message":"","projectId":"prj_uRMIndd7p1kBQ5otSkgRpD3RLMnU","traceId":"","sessionId":"","invocationId":"01K9CZDKNNJ42Z6Q82YHJX52G1","instanceId":"uADiTowSXNaq","concurrency":1}]