[{"TimeUTC":"2025-11-06 14:45:27","timestampInMs":1762440327305,"requestPath":"server-mcdcs.vercel.app/favicon.ico","requestMethod":"GET","requestQueryString":"","responseStatusCode":-1,"requestId":"gfk7g-1762440325940-01842924d673","requestUserAgent":"Mozilla/5.0 (Windows NT 10.0; Win64; x64) AppleWebKit/537.36 (KHTML, like Gecko) Chrome/142.0.0.0 Safari/537.36","level":"error","environment":"production","branch":"main","vercelCache":"","type":"lambda","function":"/server.js","host":"server-mcdcs.vercel.app","deploymentDomain":"server-mcdcs.vercel.app","deploymentId":"dpl_DXTZ13sYdb3DTyjZDb72UcQsc5rU","durationMs":-1,"region":"iad1","maxMemoryUsed":-1,"memorySize":-1,"message":"[dotenv@17.2.2] injecting env (0) from .env -- tip: ⚙️  enable debug logging with { debug: true }\n(node:4) [MONGODB DRIVER] Warning: useNewUrlParser is a deprecated option: useNewUrlParser has no effect since Node.js Driver version 4.0.0 and will be removed in the next major version\n(Use `node --trace-warnings ...` to show where the warning was created)\n(node:4) [MONGODB DRIVER] Warning: useUnifiedTopology is a deprecated option: useUnifiedTopology has no effect since Node.js Driver version 4.0.0 and will be removed in the next major version\n[dotenv@17.2.2] injecting env (0) from .env -- tip: 🛠️  run anywhere with `dotenvx run -- yourcommand`\nConnected to MongoDB Atlas\nPathError [TypeError]: Missing parameter name at index 1: *; visit https://git.new/pathToRegexpError for info\n    at name (/var/task/backend/node_modules/path-to-regexp/dist/index.js:96:19)\n    at parse (/var/task/backend/node_modules/path-to-regexp/dist/index.js:113:68)\n    at pathToRegexp (/var/task/backend/node_modules/path-to-regexp/dist/index.js:267:58)\n    at Object.match (/var/task/backend/node_modules/path-to-regexp/dist/index.js:237:30)\n    at matcher (/var/task/backend/node_modules/router/lib/layer.js:86:23)\n    at new Layer (/var/task/backend/node_modules/router/lib/layer.js:93:62)\n    at Function.route (/var/task/backend/node_modules/router/index.js:428:17)\n    at Function.route (/var/task/backend/node_modules/express/lib/application.js:257:22)\n    at app.<computed> [as get] (/var/task/backend/node_modules/express/lib/application.js:478:22)\n    at Object.<anonymous> (/var/task/backend/server.js:124:9) {\n  originalPath: '*'\n}\nNode.js process exited with exit status: 1. The logs above can help with debugging the issue.","projectId":"prj_uRMIndd7p1kBQ5otSkgRpD3RLMnU","traceId":"","sessionId":"","invocationId":"01K9CT2AWS6G65R3Q8TR676WZA","instanceId":"","concurrency":-1},{"TimeUTC":"2025-11-06 14:45:26","timestampInMs":1762440326040,"requestPath":"server-mcdcs.vercel.app/favicon.ico","requestMethod":"GET","requestQueryString":"","responseStatusCode":500,"requestId":"gfk7g-1762440325940-01842924d673","requestUserAgent":"Mozilla/5.0 (Windows NT 10.0; Win64; x64) AppleWebKit/537.36 (KHTML, like Gecko) Chrome/142.0.0.0 Safari/537.36","level":"error","environment":"production","branch":"main","vercelCache":"","type":"lambda","function":"/server.js","host":"server-mcdcs.vercel.app","deploymentDomain":"server-mcdcs.vercel.app","deploymentId":"dpl_DXTZ13sYdb3DTyjZDb72UcQsc5rU","durationMs":1248,"region":"iad1","maxMemoryUsed":161,"memorySize":2048,"message":"","projectId":"prj_uRMIndd7p1kBQ5otSkgRpD3RLMnU","traceId":"","sessionId":"","invocationId":"01K9CT2AWS6G65R3Q8TR676WZA","instanceId":"","concurrency":1},{"TimeUTC":"2025-11-06 14:45:25","timestampInMs":1762440325286,"requestPath":"server-mcdcs.vercel.app/api","requestMethod":"GET","requestQueryString":"","responseStatusCode":-1,"requestId":"t4vqc-1762440323700-ec9d0c77aecd","requestUserAgent":"Mozilla/5.0 (Windows NT 10.0; Win64; x64) AppleWebKit/537.36 (KHTML, like Gecko) Chrome/142.0.0.0 Safari/537.36","level":"error","environment":"production","branch":"main","vercelCache":"","type":"lambda","function":"/server.js","host":"server-mcdcs.vercel.app","deploymentDomain":"server-mcdcs.vercel.app","deploymentId":"dpl_DXTZ13sYdb3DTyjZDb72UcQsc5rU","durationMs":-1,"region":"iad1","maxMemoryUsed":-1,"memorySize":-1,"message":"[dotenv@17.2.2] injecting env (0) from .env -- tip: ⚙️  load multiple .env files with { path: ['.env.local', '.env'] }\n(node:4) [MONGODB DRIVER] Warning: useNewUrlParser is a deprecated option: useNewUrlParser has no effect since Node.js Driver version 4.0.0 and will be removed in the next major version\n(Use `node --trace-warnings ...` to show where the warning was created)\n(node:4) [MONGODB DRIVER] Warning: useUnifiedTopology is a deprecated option: useUnifiedTopology has no effect since Node.js Driver version 4.0.0 and will be removed in the next major version\n[dotenv@17.2.2] injecting env (0) from .env -- tip: 📡 auto-backup env with Radar: https://dotenvx.com/radar\nConnected to MongoDB Atlas\nPathError [TypeError]: Missing parameter name at index 1: *; visit https://git.new/pathToRegexpError for info\n    at name (/var/task/backend/node_modules/path-to-regexp/dist/index.js:96:19)\n    at parse (/var/task/backend/node_modules/path-to-regexp/dist/index.js:113:68)\n    at pathToRegexp (/var/task/backend/node_modules/path-to-regexp/dist/index.js:267:58)\n    at Object.match (/var/task/backend/node_modules/path-to-regexp/dist/index.js:237:30)\n    at matcher (/var/task/backend/node_modules/router/lib/layer.js:86:23)\n    at new Layer (/var/task/backend/node_modules/router/lib/layer.js:93:62)\n    at Function.route (/var/task/backend/node_modules/router/index.js:428:17)\n    at Function.route (/var/task/backend/node_modules/express/lib/application.js:257:22)\n    at app.<computed> [as get] (/var/task/backend/node_modules/express/lib/application.js:478:22)\n    at Object.<anonymous> (/var/task/backend/server.js:124:9) {\n  originalPath: '*'\n}\nNode.js process exited with exit status: 1. The logs above can help with debugging the issue.","projectId":"prj_uRMIndd7p1kBQ5otSkgRpD3RLMnU","traceId":"","sessionId":"","invocationId":"01K9CT28XR5AEDWZ0ANMY0ZRNJ","instanceId":"","concurrency":-1},{"TimeUTC":"2025-11-06 14:45:24","timestampInMs":1762440324024,"requestPath":"server-mcdcs.vercel.app/api","requestMethod":"GET","requestQueryString":"","responseStatusCode":500,"requestId":"t4vqc-1762440323700-ec9d0c77aecd","requestUserAgent":"Mozilla/5.0 (Windows NT 10.0; Win64; x64) AppleWebKit/537.36 (KHTML, like Gecko) Chrome/142.0.0.0 Safari/537.36","level":"error","environment":"production","branch":"main","vercelCache":"","type":"lambda","function":"/server.js","host":"server-mcdcs.vercel.app","deploymentDomain":"server-mcdcs.vercel.app","deploymentId":"dpl_DXTZ13sYdb3DTyjZDb72UcQsc5rU","durationMs":1246,"region":"iad1","maxMemoryUsed":161,"memorySize":2048,"message":"","projectId":"prj_uRMIndd7p1kBQ5otSkgRpD3RLMnU","traceId":"","sessionId":"","invocationId":"01K9CT28XR5AEDWZ0ANMY0ZRNJ","instanceId":"","concurrency":1},{"TimeUTC":"2025-11-06 14:42:53","timestampInMs":1762440173870,"requestPath":"server-mcdcs.vercel.app/favicon.ico","requestMethod":"GET","requestQueryString":"","responseStatusCode":-1,"requestId":"9b628-1762440172270-33c7dd7e04af","requestUserAgent":"Mozilla/5.0 (Windows NT 10.0; Win64; x64) AppleWebKit/537.36 (KHTML, like Gecko) Chrome/142.0.0.0 Safari/537.36","level":"error","environment":"production","branch":"main","vercelCache":"","type":"lambda","function":"/server.js","host":"server-mcdcs.vercel.app","deploymentDomain":"server-mcdcs.vercel.app","deploymentId":"dpl_DXTZ13sYdb3DTyjZDb72UcQsc5rU","durationMs":-1,"region":"iad1","maxMemoryUsed":-1,"memorySize":-1,"message":"[dotenv@17.2.2] injecting env (0) from .env -- tip: 🔐 encrypt with Dotenvx: https://dotenvx.com\n(node:4) [MONGODB DRIVER] Warning: useNewUrlParser is a deprecated option: useNewUrlParser has no effect since Node.js Driver version 4.0.0 and will be removed in the next major version\n(Use `node --trace-warnings ...` to show where the warning was created)\n(node:4) [MONGODB DRIVER] Warning: useUnifiedTopology is a deprecated option: useUnifiedTopology has no effect since Node.js Driver version 4.0.0 and will be removed in the next major version\n[dotenv@17.2.2] injecting env (0) from .env -- tip: ⚙️  enable debug logging with { debug: true }\nConnected to MongoDB Atlas\nPathError [TypeError]: Missing parameter name at index 1: *; visit https://git.new/pathToRegexpError for info\n    at name (/var/task/backend/node_modules/path-to-regexp/dist/index.js:96:19)\n    at parse (/var/task/backend/node_modules/path-to-regexp/dist/index.js:113:68)\n    at pathToRegexp (/var/task/backend/node_modules/path-to-regexp/dist/index.js:267:58)\n    at Object.match (/var/task/backend/node_modules/path-to-regexp/dist/index.js:237:30)\n    at matcher (/var/task/backend/node_modules/router/lib/layer.js:86:23)\n    at new Layer (/var/task/backend/node_modules/router/lib/layer.js:93:62)\n    at Function.route (/var/task/backend/node_modules/router/index.js:428:17)\n    at Function.route (/var/task/backend/node_modules/express/lib/application.js:257:22)\n    at app.<computed> [as get] (/var/task/backend/node_modules/express/lib/application.js:478:22)\n    at Object.<anonymous> (/var/task/backend/server.js:124:9) {\n  originalPath: '*'\n}\nNode.js process exited with exit status: 1. The logs above can help with debugging the issue.","projectId":"prj_uRMIndd7p1kBQ5otSkgRpD3RLMnU","traceId":"","sessionId":"","invocationId":"01K9CSXN18Y02YWNW44XQ9T2BK","instanceId":"","concurrency":-1},{"TimeUTC":"2025-11-06 14:42:52","timestampInMs":1762440172584,"requestPath":"server-mcdcs.vercel.app/favicon.ico","requestMethod":"GET","requestQueryString":"","responseStatusCode":500,"requestId":"9b628-1762440172270-33c7dd7e04af","requestUserAgent":"Mozilla/5.0 (Windows NT 10.0; Win64; x64) AppleWebKit/537.36 (KHTML, like Gecko) Chrome/142.0.0.0 Safari/537.36","level":"error","environment":"production","branch":"main","vercelCache":"","type":"lambda","function":"/server.js","host":"server-mcdcs.vercel.app","deploymentDomain":"server-mcdcs.vercel.app","deploymentId":"dpl_DXTZ13sYdb3DTyjZDb72UcQsc5rU","durationMs":1266,"region":"iad1","maxMemoryUsed":161,"memorySize":2048,"message":"","projectId":"prj_uRMIndd7p1kBQ5otSkgRpD3RLMnU","traceId":"","sessionId":"","invocationId":"01K9CSXN18Y02YWNW44XQ9T2BK","instanceId":"","concurrency":1},{"TimeUTC":"2025-11-06 14:42:51","timestampInMs":1762440171563,"requestPath":"server-mcdcs.vercel.app/api","requestMethod":"GET","requestQueryString":"","responseStatusCode":-1,"requestId":"vlscx-1762440170190-032755fb2e86","requestUserAgent":"Mozilla/5.0 (Windows NT 10.0; Win64; x64) AppleWebKit/537.36 (KHTML, like Gecko) Chrome/142.0.0.0 Safari/537.36","level":"error","environment":"production","branch":"main","vercelCache":"","type":"lambda","function":"/server.js","host":"server-mcdcs.vercel.app","deploymentDomain":"server-mcdcs.vercel.app","deploymentId":"dpl_DXTZ13sYdb3DTyjZDb72UcQsc5rU","durationMs":-1,"region":"iad1","maxMemoryUsed":-1,"memorySize":-1,"message":"[dotenv@17.2.2] injecting env (0) from .env -- tip: ⚙️  override existing env vars with { override: true }\n(node:4) [MONGODB DRIVER] Warning: useNewUrlParser is a deprecated option: useNewUrlParser has no effect since Node.js Driver version 4.0.0 and will be removed in the next major version\n(Use `node --trace-warnings ...` to show where the warning was created)\n(node:4) [MONGODB DRIVER] Warning: useUnifiedTopology is a deprecated option: useUnifiedTopology has no effect since Node.js Driver version 4.0.0 and will be removed in the next major version\n[dotenv@17.2.2] injecting env (0) from .env -- tip: 🔐 encrypt with Dotenvx: https://dotenvx.com\nConnected to MongoDB Atlas\nPathError [TypeError]: Missing parameter name at index 1: *; visit https://git.new/pathToRegexpError for info\n    at name (/var/task/backend/node_modules/path-to-regexp/dist/index.js:96:19)\n    at parse (/var/task/backend/node_modules/path-to-regexp/dist/index.js:113:68)\n    at pathToRegexp (/var/task/backend/node_modules/path-to-regexp/dist/index.js:267:58)\n    at Object.match (/var/task/backend/node_modules/path-to-regexp/dist/index.js:237:30)\n    at matcher (/var/task/backend/node_modules/router/lib/layer.js:86:23)\n    at new Layer (/var/task/backend/node_modules/router/lib/layer.js:93:62)\n    at Function.route (/var/task/backend/node_modules/router/index.js:428:17)\n    at Function.route (/var/task/backend/node_modules/express/lib/application.js:257:22)\n    at app.<computed> [as get] (/var/task/backend/node_modules/express/lib/application.js:478:22)\n    at Object.<anonymous> (/var/task/backend/server.js:124:9) {\n  originalPath: '*'\n}\nNode.js process exited with exit status: 1. The logs above can help with debugging the issue.","projectId":"prj_uRMIndd7p1kBQ5otSkgRpD3RLMnU","traceId":"","sessionId":"","invocationId":"01K9CSXJSQN6RMPPTDBEH6FTMM","instanceId":"","concurrency":-1},{"TimeUTC":"2025-11-06 14:42:50","timestampInMs":1762440170295,"requestPath":"server-mcdcs.vercel.app/api","requestMethod":"GET","requestQueryString":"","responseStatusCode":500,"requestId":"vlscx-1762440170190-032755fb2e86","requestUserAgent":"Mozilla/5.0 (Windows NT 10.0; Win64; x64) AppleWebKit/537.36 (KHTML, like Gecko) Chrome/142.0.0.0 Safari/537.36","level":"error","environment":"production","branch":"main","vercelCache":"","type":"lambda","function":"/server.js","host":"server-mcdcs.vercel.app","deploymentDomain":"server-mcdcs.vercel.app","deploymentId":"dpl_DXTZ13sYdb3DTyjZDb72UcQsc5rU","durationMs":1251,"region":"iad1","maxMemoryUsed":161,"memorySize":2048,"message":"","projectId":"prj_uRMIndd7p1kBQ5otSkgRpD3RLMnU","traceId":"","sessionId":"","invocationId":"01K9CSXJSQN6RMPPTDBEH6FTMM","instanceId":"","concurrency":1},{"TimeUTC":"2025-11-06 14:42:37","timestampInMs":1762440157764,"requestPath":"server-mcdcs.vercel.app/favicon.ico","requestMethod":"GET","requestQueryString":"","responseStatusCode":-1,"requestId":"szzdq-1762440156185-b5ed05c1fc8e","requestUserAgent":"Mozilla/5.0 (Windows NT 10.0; Win64; x64) AppleWebKit/537.36 (KHTML, like Gecko) Chrome/142.0.0.0 Safari/537.36","level":"error","environment":"production","branch":"main","vercelCache":"","type":"lambda","function":"/server.js","host":"server-mcdcs.vercel.app","deploymentDomain":"server-mcdcs.vercel.app","deploymentId":"dpl_DXTZ13sYdb3DTyjZDb72UcQsc5rU","durationMs":-1,"region":"iad1","maxMemoryUsed":-1,"memorySize":-1,"message":"[dotenv@17.2.2] injecting env (0) from .env -- tip: 🔐 prevent building .env in docker: https://dotenvx.com/prebuild\n(node:4) [MONGODB DRIVER] Warning: useNewUrlParser is a deprecated option: useNewUrlParser has no effect since Node.js Driver version 4.0.0 and will be removed in the next major version\n(Use `node --trace-warnings ...` to show where the warning was created)\n(node:4) [MONGODB DRIVER] Warning: useUnifiedTopology is a deprecated option: useUnifiedTopology has no effect since Node.js Driver version 4.0.0 and will be removed in the next major version\n[dotenv@17.2.2] injecting env (0) from .env -- tip: 🔐 prevent building .env in docker: https://dotenvx.com/prebuild\nConnected to MongoDB Atlas\nPathError [TypeError]: Missing parameter name at index 1: *; visit https://git.new/pathToRegexpError for info\n    at name (/var/task/backend/node_modules/path-to-regexp/dist/index.js:96:19)\n    at parse (/var/task/backend/node_modules/path-to-regexp/dist/index.js:113:68)\n    at pathToRegexp (/var/task/backend/node_modules/path-to-regexp/dist/index.js:267:58)\n    at Object.match (/var/task/backend/node_modules/path-to-regexp/dist/index.js:237:30)\n    at matcher (/var/task/backend/node_modules/router/lib/layer.js:86:23)\n    at new Layer (/var/task/backend/node_modules/router/lib/layer.js:93:62)\n    at Function.route (/var/task/backend/node_modules/router/index.js:428:17)\n    at Function.route (/var/task/backend/node_modules/express/lib/application.js:257:22)\n    at app.<computed> [as get] (/var/task/backend/node_modules/express/lib/application.js:478:22)\n    at Object.<anonymous> (/var/task/backend/server.js:124:9) {\n  originalPath: '*'\n}\nNode.js process exited with exit status: 1. The logs above can help with debugging the issue.","projectId":"prj_uRMIndd7p1kBQ5otSkgRpD3RLMnU","traceId":"","sessionId":"","invocationId":"01K9CSX5AP54T75GG8SGBA3H6V","instanceId":"","concurrency":-1},{"TimeUTC":"2025-11-06 14:42:36","timestampInMs":1762440156502,"requestPath":"server-mcdcs.vercel.app/favicon.ico","requestMethod":"GET","requestQueryString":"","responseStatusCode":500,"requestId":"szzdq-1762440156185-b5ed05c1fc8e","requestUserAgent":"Mozilla/5.0 (Windows NT 10.0; Win64; x64) AppleWebKit/537.36 (KHTML, like Gecko) Chrome/142.0.0.0 Safari/537.36","level":"error","environment":"production","branch":"main","vercelCache":"","type":"lambda","function":"/server.js","host":"server-mcdcs.vercel.app","deploymentDomain":"server-mcdcs.vercel.app","deploymentId":"dpl_DXTZ13sYdb3DTyjZDb72UcQsc5rU","durationMs":1245,"region":"iad1","maxMemoryUsed":167,"memorySize":2048,"message":"","projectId":"prj_uRMIndd7p1kBQ5otSkgRpD3RLMnU","traceId":"","sessionId":"","invocationId":"01K9CSX5AP54T75GG8SGBA3H6V","instanceId":"","concurrency":1},{"TimeUTC":"2025-11-06 14:42:35","timestampInMs":1762440155797,"requestPath":"server-mcdcs.vercel.app/","requestMethod":"GET","requestQueryString":"","responseStatusCode":-1,"requestId":"pj54q-1762440154385-d4193459d2fe","requestUserAgent":"Mozilla/5.0 (Windows NT 10.0; Win64; x64) AppleWebKit/537.36 (KHTML, like Gecko) Chrome/142.0.0.0 Safari/537.36","level":"error","environment":"production","branch":"main","vercelCache":"","type":"lambda","function":"/server.js","host":"server-mcdcs.vercel.app","deploymentDomain":"server-mcdcs.vercel.app","deploymentId":"dpl_DXTZ13sYdb3DTyjZDb72UcQsc5rU","durationMs":-1,"region":"iad1","maxMemoryUsed":-1,"memorySize":-1,"message":"[dotenv@17.2.2] injecting env (0) from .env -- tip: 📡 observe env with Radar: https://dotenvx.com/radar\n(node:4) [MONGODB DRIVER] Warning: useNewUrlParser is a deprecated option: useNewUrlParser has no effect since Node.js Driver version 4.0.0 and will be removed in the next major version\n(Use `node --trace-warnings ...` to show where the warning was created)\n(node:4) [MONGODB DRIVER] Warning: useUnifiedTopology is a deprecated option: useUnifiedTopology has no effect since Node.js Driver version 4.0.0 and will be removed in the next major version\n[dotenv@17.2.2] injecting env (0) from .env -- tip: 🔐 prevent building .env in docker: https://dotenvx.com/prebuild\nConnected to MongoDB Atlas\nPathError [TypeError]: Missing parameter name at index 1: *; visit https://git.new/pathToRegexpError for info\n    at name (/var/task/backend/node_modules/path-to-regexp/dist/index.js:96:19)\n    at parse (/var/task/backend/node_modules/path-to-regexp/dist/index.js:113:68)\n    at pathToRegexp (/var/task/backend/node_modules/path-to-regexp/dist/index.js:267:58)\n    at Object.match (/var/task/backend/node_modules/path-to-regexp/dist/index.js:237:30)\n    at matcher (/var/task/backend/node_modules/router/lib/layer.js:86:23)\n    at new Layer (/var/task/backend/node_modules/router/lib/layer.js:93:62)\n    at Function.route (/var/task/backend/node_modules/router/index.js:428:17)\n    at Function.route (/var/task/backend/node_modules/express/lib/application.js:257:22)\n    at app.<computed> [as get] (/var/task/backend/node_modules/express/lib/application.js:478:22)\n    at Object.<anonymous> (/var/task/backend/server.js:124:9) {\n  originalPath: '*'\n}\nNode.js process exited with exit status: 1. The logs above can help with debugging the issue.","projectId":"prj_uRMIndd7p1kBQ5otSkgRpD3RLMnU","traceId":"","sessionId":"","invocationId":"01K9CSX3BSN0SKXVAQ3844E7C4","instanceId":"","concurrency":-1},{"TimeUTC":"2025-11-06 14:42:34","timestampInMs":1762440154489,"requestPath":"server-mcdcs.vercel.app/","requestMethod":"GET","requestQueryString":"","responseStatusCode":500,"requestId":"pj54q-1762440154385-d4193459d2fe","requestUserAgent":"Mozilla/5.0 (Windows NT 10.0; Win64; x64) AppleWebKit/537.36 (KHTML, like Gecko) Chrome/142.0.0.0 Safari/537.36","level":"error","environment":"production","branch":"main","vercelCache":"","type":"lambda","function":"/server.js","host":"server-mcdcs.vercel.app","deploymentDomain":"server-mcdcs.vercel.app","deploymentId":"dpl_DXTZ13sYdb3DTyjZDb72UcQsc5rU","durationMs":1286,"region":"iad1","maxMemoryUsed":161,"memorySize":2048,"message":"","projectId":"prj_uRMIndd7p1kBQ5otSkgRpD3RLMnU","traceId":"","sessionId":"","invocationId":"01K9CSX3BSN0SKXVAQ3844E7C4","instanceId":"","concurrency":1},{"TimeUTC":"2025-11-06 14:40:35","timestampInMs":1762440035718,"requestPath":"multi-college-data-collection-system-9cwyx1q63.vercel.app/","requestMethod":"GET","requestQueryString":"","responseStatusCode":-1,"requestId":"6s6mg-1762440034423-f15f943efe4d","requestUserAgent":"vercel-favicon/1.0","level":"error","environment":"production","branch":"main","vercelCache":"","type":"lambda","function":"/server.js","host":"multi-college-data-collection-system-9cwyx1q63.vercel.app","deploymentDomain":"multi-college-data-collection-system-9cwyx1q63.vercel.app","deploymentId":"dpl_DXTZ13sYdb3DTyjZDb72UcQsc5rU","durationMs":-1,"region":"iad1","maxMemoryUsed":-1,"memorySize":-1,"message":"[dotenv@17.2.2] injecting env (0) from .env -- tip: 📡 auto-backup env with Radar: https://dotenvx.com/radar\n(node:4) [MONGODB DRIVER] Warning: useNewUrlParser is a deprecated option: useNewUrlParser has no effect since Node.js Driver version 4.0.0 and will be removed in the next major version\n(Use `node --trace-warnings ...` to show where the warning was created)\n(node:4) [MONGODB DRIVER] Warning: useUnifiedTopology is a deprecated option: useUnifiedTopology has no effect since Node.js Driver version 4.0.0 and will be removed in the next major version\n[dotenv@17.2.2] injecting env (0) from .env -- tip: 📡 auto-backup env with Radar: https://dotenvx.com/radar\nConnected to MongoDB Atlas\nPathError [TypeError]: Missing parameter name at index 1: *; visit https://git.new/pathToRegexpError for info\n    at name (/var/task/backend/node_modules/path-to-regexp/dist/index.js:96:19)\n    at parse (/var/task/backend/node_modules/path-to-regexp/dist/index.js:113:68)\n    at pathToRegexp (/var/task/backend/node_modules/path-to-regexp/dist/index.js:267:58)\n    at Object.match (/var/task/backend/node_modules/path-to-regexp/dist/index.js:237:30)\n    at matcher (/var/task/backend/node_modules/router/lib/layer.js:86:23)\n    at new Layer (/var/task/backend/node_modules/router/lib/layer.js:93:62)\n    at Function.route (/var/task/backend/node_modules/router/index.js:428:17)\n    at Function.route (/var/task/backend/node_modules/express/lib/application.js:257:22)\n    at app.<computed> [as get] (/var/task/backend/node_modules/express/lib/application.js:478:22)\n    at Object.<anonymous> (/var/task/backend/server.js:124:9) {\n  originalPath: '*'\n}\nNode.js process exited with exit status: 1. The logs above can help with debugging the issue.","projectId":"prj_uRMIndd7p1kBQ5otSkgRpD3RLMnU","traceId":"","sessionId":"","invocationId":"01K9CSSE52N02FCW8Q1B1A8JKK","instanceId":"","concurrency":-1},{"TimeUTC":"2025-11-06 14:40:34","timestampInMs":1762440034466,"requestPath":"multi-college-data-collection-system-9cwyx1q63.vercel.app/","requestMethod":"GET","requestQueryString":"","responseStatusCode":500,"requestId":"6s6mg-1762440034423-f15f943efe4d","requestUserAgent":"vercel-favicon/1.0","level":"error","environment":"production","branch":"main","vercelCache":"","type":"lambda","function":"/server.js","host":"multi-college-data-collection-system-9cwyx1q63.vercel.app","deploymentDomain":"multi-college-data-collection-system-9cwyx1q63.vercel.app","deploymentId":"dpl_DXTZ13sYdb3DTyjZDb72UcQsc5rU","durationMs":1229,"region":"iad1","maxMemoryUsed":160,"memorySize":2048,"message":"","projectId":"prj_uRMIndd7p1kBQ5otSkgRpD3RLMnU","traceId":"","sessionId":"","invocationId":"01K9CSSE52N02FCW8Q1B1A8JKK","instanceId":"","concurrency":1},{"TimeUTC":"2025-11-06 14:40:33","timestampInMs":1762440033292,"requestPath":"multi-college-data-collection-system-9cwyx1q63.vercel.app/","requestMethod":"GET","requestQueryString":"","responseStatusCode":-1,"requestId":"rt84x-1762440032014-076b465f6d9f","requestUserAgent":"vercel-favicon/1.0","level":"error","environment":"production","branch":"main","vercelCache":"","type":"lambda","function":"/server.js","host":"multi-college-data-collection-system-9cwyx1q63.vercel.app","deploymentDomain":"multi-college-data-collection-system-9cwyx1q63.vercel.app","deploymentId":"dpl_DXTZ13sYdb3DTyjZDb72UcQsc5rU","durationMs":-1,"region":"iad1","maxMemoryUsed":-1,"memorySize":-1,"message":"[dotenv@17.2.2] injecting env (0) from .env -- tip: 📡 observe env with Radar: https://dotenvx.com/radar\n(node:4) [MONGODB DRIVER] Warning: useNewUrlParser is a deprecated option: useNewUrlParser has no effect since Node.js Driver version 4.0.0 and will be removed in the next major version\n(Use `node --trace-warnings ...` to show where the warning was created)\n(node:4) [MONGODB DRIVER] Warning: useUnifiedTopology is a deprecated option: useUnifiedTopology has no effect since Node.js Driver version 4.0.0 and will be removed in the next major version\n[dotenv@17.2.2] injecting env (0) from .env -- tip: ⚙️  suppress all logs with { quiet: true }\nConnected to MongoDB Atlas\nPathError [TypeError]: Missing parameter name at index 1: *; visit https://git.new/pathToRegexpError for info\n    at name (/var/task/backend/node_modules/path-to-regexp/dist/index.js:96:19)\n    at parse (/var/task/backend/node_modules/path-to-regexp/dist/index.js:113:68)\n    at pathToRegexp (/var/task/backend/node_modules/path-to-regexp/dist/index.js:267:58)\n    at Object.match (/var/task/backend/node_modules/path-to-regexp/dist/index.js:237:30)\n    at matcher (/var/task/backend/node_modules/router/lib/layer.js:86:23)\n    at new Layer (/var/task/backend/node_modules/router/lib/layer.js:93:62)\n    at Function.route (/var/task/backend/node_modules/router/index.js:428:17)\n    at Function.route (/var/task/backend/node_modules/express/lib/application.js:257:22)\n    at app.<computed> [as get] (/var/task/backend/node_modules/express/lib/application.js:478:22)\n    at Object.<anonymous> (/var/task/backend/server.js:124:9) {\n  originalPath: '*'\n}\nNode.js process exited with exit status: 1. The logs above can help with debugging the issue.","projectId":"prj_uRMIndd7p1kBQ5otSkgRpD3RLMnU","traceId":"","sessionId":"","invocationId":"01K9CSSBSR8NDKF7R6BR9NSV1K","instanceId":"","concurrency":-1},{"TimeUTC":"2025-11-06 14:40:32","timestampInMs":1762440032056,"requestPath":"multi-college-data-collection-system-9cwyx1q63.vercel.app/","requestMethod":"GET","requestQueryString":"","responseStatusCode":500,"requestId":"rt84x-1762440032014-076b465f6d9f","requestUserAgent":"vercel-favicon/1.0","level":"error","environment":"production","branch":"main","vercelCache":"","type":"lambda","function":"/server.js","host":"multi-college-data-collection-system-9cwyx1q63.vercel.app","deploymentDomain":"multi-college-data-collection-system-9cwyx1q63.vercel.app","deploymentId":"dpl_DXTZ13sYdb3DTyjZDb72UcQsc5rU","durationMs":1221,"region":"iad1","maxMemoryUsed":161,"memorySize":2048,"message":"","projectId":"prj_uRMIndd7p1kBQ5otSkgRpD3RLMnU","traceId":"","sessionId":"","invocationId":"01K9CSSBSR8NDKF7R6BR9NSV1K","instanceId":"","concurrency":1},{"TimeUTC":"2025-11-06 14:39:11","timestampInMs":1762439951332,"requestPath":"multi-college-data-collection-system-9cwyx1q63.vercel.app/favicon.ico","requestMethod":"GET","requestQueryString":"","responseStatusCode":-1,"requestId":"btzdb-1762439949540-43b65ab6d9e3","requestUserAgent":"Mozilla/5.0 (Windows NT 10.0; Win64; x64) AppleWebKit/537.36 (KHTML, like Gecko) Chrome/142.0.0.0 Safari/537.36","level":"error","environment":"production","branch":"main","vercelCache":"","type":"lambda","function":"/server.js","host":"multi-college-data-collection-system-9cwyx1q63.vercel.app","deploymentDomain":"multi-college-data-collection-system-9cwyx1q63.vercel.app","deploymentId":"dpl_DXTZ13sYdb3DTyjZDb72UcQsc5rU","durationMs":-1,"region":"iad1","maxMemoryUsed":-1,"memorySize":-1,"message":"[dotenv@17.2.2] injecting env (0) from .env -- tip: 📡 version env with Radar: https://dotenvx.com/radar\n(node:4) [MONGODB DRIVER] Warning: useNewUrlParser is a deprecated option: useNewUrlParser has no effect since Node.js Driver version 4.0.0 and will be removed in the next major version\n(Use `node --trace-warnings ...` to show where the warning was created)\n(node:4) [MONGODB DRIVER] Warning: useUnifiedTopology is a deprecated option: useUnifiedTopology has no effect since Node.js Driver version 4.0.0 and will be removed in the next major version\n[dotenv@17.2.2] injecting env (0) from .env -- tip: ⚙️  write to custom object with { processEnv: myObject }\nConnected to MongoDB Atlas\nPathError [TypeError]: Missing parameter name at index 1: *; visit https://git.new/pathToRegexpError for info\n    at name (/var/task/backend/node_modules/path-to-regexp/dist/index.js:96:19)\n    at parse (/var/task/backend/node_modules/path-to-regexp/dist/index.js:113:68)\n    at pathToRegexp (/var/task/backend/node_modules/path-to-regexp/dist/index.js:267:58)\n    at Object.match (/var/task/backend/node_modules/path-to-regexp/dist/index.js:237:30)\n    at matcher (/var/task/backend/node_modules/router/lib/layer.js:86:23)\n    at new Layer (/var/task/backend/node_modules/router/lib/layer.js:93:62)\n    at Function.route (/var/task/backend/node_modules/router/index.js:428:17)\n    at Function.route (/var/task/backend/node_modules/express/lib/application.js:257:22)\n    at app.<computed> [as get] (/var/task/backend/node_modules/express/lib/application.js:478:22)\n    at Object.<anonymous> (/var/task/backend/server.js:124:9) {\n  originalPath: '*'\n}\nNode.js process exited with exit status: 1. The logs above can help with debugging the issue.","projectId":"prj_uRMIndd7p1kBQ5otSkgRpD3RLMnU","traceId":"","sessionId":"","invocationId":"01K9CSPVHAWZZFE8105PD5K5XB","instanceId":"","concurrency":-1},{"TimeUTC":"2025-11-06 14:39:09","timestampInMs":1762439949866,"requestPath":"multi-college-data-collection-system-9cwyx1q63.vercel.app/favicon.ico","requestMethod":"GET","requestQueryString":"","responseStatusCode":500,"requestId":"btzdb-1762439949540-43b65ab6d9e3","requestUserAgent":"Mozilla/5.0 (Windows NT 10.0; Win64; x64) AppleWebKit/537.36 (KHTML, like Gecko) Chrome/142.0.0.0 Safari/537.36","level":"error","environment":"production","branch":"main","vercelCache":"","type":"lambda","function":"/server.js","host":"multi-college-data-collection-system-9cwyx1q63.vercel.app","deploymentDomain":"multi-college-data-collection-system-9cwyx1q63.vercel.app","deploymentId":"dpl_DXTZ13sYdb3DTyjZDb72UcQsc5rU","durationMs":1449,"region":"iad1","maxMemoryUsed":161,"memorySize":2048,"message":"","projectId":"prj_uRMIndd7p1kBQ5otSkgRpD3RLMnU","traceId":"","sessionId":"","invocationId":"01K9CSPVHAWZZFE8105PD5K5XB","instanceId":"","concurrency":1},{"TimeUTC":"2025-11-06 14:39:09","timestampInMs":1762439949221,"requestPath":"multi-college-data-collection-system-9cwyx1q63.vercel.app/","requestMethod":"GET","requestQueryString":"","responseStatusCode":-1,"requestId":"xnj9f-1762439947330-d5b703ee7794","requestUserAgent":"Mozilla/5.0 (Windows NT 10.0; Win64; x64) AppleWebKit/537.36 (KHTML, like Gecko) Chrome/142.0.0.0 Safari/537.36","level":"error","environment":"production","branch":"main","vercelCache":"","type":"lambda","function":"/server.js","host":"multi-college-data-collection-system-9cwyx1q63.vercel.app","deploymentDomain":"multi-college-data-collection-system-9cwyx1q63.vercel.app","deploymentId":"dpl_DXTZ13sYdb3DTyjZDb72UcQsc5rU","durationMs":-1,"region":"iad1","maxMemoryUsed":-1,"memorySize":-1,"message":"[dotenv@17.2.2] injecting env (0) from .env -- tip: 📡 auto-backup env with Radar: https://dotenvx.com/radar\n(node:4) [MONGODB DRIVER] Warning: useNewUrlParser is a deprecated option: useNewUrlParser has no effect since Node.js Driver version 4.0.0 and will be removed in the next major version\n(Use `node --trace-warnings ...` to show where the warning was created)\n(node:4) [MONGODB DRIVER] Warning: useUnifiedTopology is a deprecated option: useUnifiedTopology has no effect since Node.js Driver version 4.0.0 and will be removed in the next major version\n[dotenv@17.2.2] injecting env (0) from .env -- tip: 🔐 prevent committing .env to code: https://dotenvx.com/precommit\nConnected to MongoDB Atlas\nPathError [TypeError]: Missing parameter name at index 1: *; visit https://git.new/pathToRegexpError for info\n    at name (/var/task/backend/node_modules/path-to-regexp/dist/index.js:96:19)\n    at parse (/var/task/backend/node_modules/path-to-regexp/dist/index.js:113:68)\n    at pathToRegexp (/var/task/backend/node_modules/path-to-regexp/dist/index.js:267:58)\n    at Object.match (/var/task/backend/node_modules/path-to-regexp/dist/index.js:237:30)\n    at matcher (/var/task/backend/node_modules/router/lib/layer.js:86:23)\n    at new Layer (/var/task/backend/node_modules/router/lib/layer.js:93:62)\n    at Function.route (/var/task/backend/node_modules/router/index.js:428:17)\n    at Function.route (/var/task/backend/node_modules/express/lib/application.js:257:22)\n    at app.<computed> [as get] (/var/task/backend/node_modules/express/lib/application.js:478:22)\n    at Object.<anonymous> (/var/task/backend/server.js:124:9) {\n  originalPath: '*'\n}\nNode.js process exited with exit status: 1. The logs above can help with debugging the issue.","projectId":"prj_uRMIndd7p1kBQ5otSkgRpD3RLMnU","traceId":"","sessionId":"","invocationId":"01K9CSPSCNPFD9NF4PRSVQP9DN","instanceId":"","concurrency":-1},{"TimeUTC":"2025-11-06 14:39:07","timestampInMs":1762439947669,"requestPath":"multi-college-data-collection-system-9cwyx1q63.vercel.app/","requestMethod":"GET","requestQueryString":"","responseStatusCode":500,"requestId":"xnj9f-1762439947330-d5b703ee7794","requestUserAgent":"Mozilla/5.0 (Windows NT 10.0; Win64; x64) AppleWebKit/537.36 (KHTML, like Gecko) Chrome/142.0.0.0 Safari/537.36","level":"error","environment":"production","branch":"main","vercelCache":"","type":"lambda","function":"/server.js","host":"multi-college-data-collection-system-9cwyx1q63.vercel.app","deploymentDomain":"multi-college-data-collection-system-9cwyx1q63.vercel.app","deploymentId":"dpl_DXTZ13sYdb3DTyjZDb72UcQsc5rU","durationMs":1531,"region":"iad1","maxMemoryUsed":160,"memorySize":2048,"message":"","projectId":"prj_uRMIndd7p1kBQ5otSkgRpD3RLMnU","traceId":"","sessionId":"","invocationId":"01K9CSPSCNPFD9NF4PRSVQP9DN","instanceId":"","concurrency":1},{"TimeUTC":"2025-11-06 14:38:44","timestampInMs":1762439924741,"requestPath":"multi-college-data-collection-system-9cwyx1q63.vercel.app/favicon.png","requestMethod":"GET","requestQueryString":"","responseStatusCode":-1,"requestId":"rbprp-1762439923393-d5ede9f305b4","requestUserAgent":"vercel-favicon/1.0","level":"error","environment":"production","branch":"main","vercelCache":"","type":"lambda","function":"/server.js","host":"multi-college-data-collection-system-9cwyx1q63.vercel.app","deploymentDomain":"multi-college-data-collection-system-9cwyx1q63.vercel.app","deploymentId":"dpl_DXTZ13sYdb3DTyjZDb72UcQsc5rU","durationMs":-1,"region":"iad1","maxMemoryUsed":-1,"memorySize":-1,"message":"[dotenv@17.2.2] injecting env (0) from .env -- tip: ⚙️  load multiple .env files with { path: ['.env.local', '.env'] }\n(node:4) [MONGODB DRIVER] Warning: useNewUrlParser is a deprecated option: useNewUrlParser has no effect since Node.js Driver version 4.0.0 and will be removed in the next major version\n(Use `node --trace-warnings ...` to show where the warning was created)\n(node:4) [MONGODB DRIVER] Warning: useUnifiedTopology is a deprecated option: useUnifiedTopology has no effect since Node.js Driver version 4.0.0 and will be removed in the next major version\n[dotenv@17.2.2] injecting env (0) from .env -- tip: 🔐 prevent building .env in docker: https://dotenvx.com/prebuild\nConnected to MongoDB Atlas\nPathError [TypeError]: Missing parameter name at index 1: *; visit https://git.new/pathToRegexpError for info\n    at name (/var/task/backend/node_modules/path-to-regexp/dist/index.js:96:19)\n    at parse (/var/task/backend/node_modules/path-to-regexp/dist/index.js:113:68)\n    at pathToRegexp (/var/task/backend/node_modules/path-to-regexp/dist/index.js:267:58)\n    at Object.match (/var/task/backend/node_modules/path-to-regexp/dist/index.js:237:30)\n    at matcher (/var/task/backend/node_modules/router/lib/layer.js:86:23)\n    at new Layer (/var/task/backend/node_modules/router/lib/layer.js:93:62)\n    at Function.route (/var/task/backend/node_modules/router/index.js:428:17)\n    at Function.route (/var/task/backend/node_modules/express/lib/application.js:257:22)\n    at app.<computed> [as get] (/var/task/backend/node_modules/express/lib/application.js:478:22)\n    at Object.<anonymous> (/var/task/backend/server.js:124:9) {\n  originalPath: '*'\n}\nNode.js process exited with exit status: 1. The logs above can help with debugging the issue.","projectId":"prj_uRMIndd7p1kBQ5otSkgRpD3RLMnU","traceId":"","sessionId":"","invocationId":"01K9CSP1R8TZZQF80MHQFSR3KJ","instanceId":"","concurrency":-1},{"TimeUTC":"2025-11-06 14:38:43","timestampInMs":1762439923464,"requestPath":"multi-college-data-collection-system-9cwyx1q63.vercel.app/favicon.png","requestMethod":"GET","requestQueryString":"","responseStatusCode":500,"requestId":"rbprp-1762439923393-d5ede9f305b4","requestUserAgent":"vercel-favicon/1.0","level":"error","environment":"production","branch":"main","vercelCache":"","type":"lambda","function":"/server.js","host":"multi-college-data-collection-system-9cwyx1q63.vercel.app","deploymentDomain":"multi-college-data-collection-system-9cwyx1q63.vercel.app","deploymentId":"dpl_DXTZ13sYdb3DTyjZDb72UcQsc5rU","durationMs":1261,"region":"iad1","maxMemoryUsed":162,"memorySize":2048,"message":"","projectId":"prj_uRMIndd7p1kBQ5otSkgRpD3RLMnU","traceId":"","sessionId":"","invocationId":"01K9CSP1R8TZZQF80MHQFSR3KJ","instanceId":"","concurrency":1},{"TimeUTC":"2025-11-06 14:38:41","timestampInMs":1762439921318,"requestPath":"multi-college-data-collection-system-9cwyx1q63.vercel.app/favicon.png","requestMethod":"GET","requestQueryString":"","responseStatusCode":-1,"requestId":"k7b2t-1762439920014-2848697b1597","requestUserAgent":"vercel-favicon/1.0","level":"error","environment":"production","branch":"main","vercelCache":"","type":"lambda","function":"/server.js","host":"multi-college-data-collection-system-9cwyx1q63.vercel.app","deploymentDomain":"multi-college-data-collection-system-9cwyx1q63.vercel.app","deploymentId":"dpl_DXTZ13sYdb3DTyjZDb72UcQsc5rU","durationMs":-1,"region":"iad1","maxMemoryUsed":-1,"memorySize":-1,"message":"[dotenv@17.2.2] injecting env (0) from .env -- tip: 📡 version env with Radar: https://dotenvx.com/radar\n(node:4) [MONGODB DRIVER] Warning: useNewUrlParser is a deprecated option: useNewUrlParser has no effect since Node.js Driver version 4.0.0 and will be removed in the next major version\n(Use `node --trace-warnings ...` to show where the warning was created)\n(node:4) [MONGODB DRIVER] Warning: useUnifiedTopology is a deprecated option: useUnifiedTopology has no effect since Node.js Driver version 4.0.0 and will be removed in the next major version\n[dotenv@17.2.2] injecting env (0) from .env -- tip: 📡 version env with Radar: https://dotenvx.com/radar\nConnected to MongoDB Atlas\nPathError [TypeError]: Missing parameter name at index 1: *; visit https://git.new/pathToRegexpError for info\n    at name (/var/task/backend/node_modules/path-to-regexp/dist/index.js:96:19)\n    at parse (/var/task/backend/node_modules/path-to-regexp/dist/index.js:113:68)\n    at pathToRegexp (/var/task/backend/node_modules/path-to-regexp/dist/index.js:267:58)\n    at Object.match (/var/task/backend/node_modules/path-to-regexp/dist/index.js:237:30)\n    at matcher (/var/task/backend/node_modules/router/lib/layer.js:86:23)\n    at new Layer (/var/task/backend/node_modules/router/lib/layer.js:93:62)\n    at Function.route (/var/task/backend/node_modules/router/index.js:428:17)\n    at Function.route (/var/task/backend/node_modules/express/lib/application.js:257:22)\n    at app.<computed> [as get] (/var/task/backend/node_modules/express/lib/application.js:478:22)\n    at Object.<anonymous> (/var/task/backend/server.js:124:9) {\n  originalPath: '*'\n}\nNode.js process exited with exit status: 1. The logs above can help with debugging the issue.","projectId":"prj_uRMIndd7p1kBQ5otSkgRpD3RLMnU","traceId":"","sessionId":"","invocationId":"01K9CSNYDZNWCK4YD5QGNM5T3Z","instanceId":"","concurrency":-1},{"TimeUTC":"2025-11-06 14:38:40","timestampInMs":1762439920063,"requestPath":"multi-college-data-collection-system-9cwyx1q63.vercel.app/favicon.png","requestMethod":"GET","requestQueryString":"","responseStatusCode":500,"requestId":"k7b2t-1762439920014-2848697b1597","requestUserAgent":"vercel-favicon/1.0","level":"error","environment":"production","branch":"main","vercelCache":"","type":"lambda","function":"/server.js","host":"multi-college-data-collection-system-9cwyx1q63.vercel.app","deploymentDomain":"multi-college-data-collection-system-9cwyx1q63.vercel.app","deploymentId":"dpl_DXTZ13sYdb3DTyjZDb72UcQsc5rU","durationMs":1238,"region":"iad1","maxMemoryUsed":162,"memorySize":2048,"message":"","projectId":"prj_uRMIndd7p1kBQ5otSkgRpD3RLMnU","traceId":"","sessionId":"","invocationId":"01K9CSNYDZNWCK4YD5QGNM5T3Z","instanceId":"","concurrency":1},{"TimeUTC":"2025-11-06 14:38:38","timestampInMs":1762439918905,"requestPath":"multi-college-data-collection-system-9cwyx1q63.vercel.app/favicon.png","requestMethod":"GET","requestQueryString":"","responseStatusCode":-1,"requestId":"lfzld-1762439917580-2906afa814a6","requestUserAgent":"vercel-favicon/1.0","level":"error","environment":"production","branch":"main","vercelCache":"","type":"lambda","function":"/server.js","host":"multi-college-data-collection-system-9cwyx1q63.vercel.app","deploymentDomain":"multi-college-data-collection-system-9cwyx1q63.vercel.app","deploymentId":"dpl_DXTZ13sYdb3DTyjZDb72UcQsc5rU","durationMs":-1,"region":"iad1","maxMemoryUsed":-1,"memorySize":-1,"message":"[dotenv@17.2.2] injecting env (0) from .env -- tip: ⚙️  write to custom object with { processEnv: myObject }\n(node:4) [MONGODB DRIVER] Warning: useNewUrlParser is a deprecated option: useNewUrlParser has no effect since Node.js Driver version 4.0.0 and will be removed in the next major version\n(Use `node --trace-warnings ...` to show where the warning was created)\n(node:4) [MONGODB DRIVER] Warning: useUnifiedTopology is a deprecated option: useUnifiedTopology has no effect since Node.js Driver version 4.0.0 and will be removed in the next major version\n[dotenv@17.2.2] injecting env (0) from .env -- tip: ⚙️  specify custom .env file path with { path: '/custom/path/.env' }\nConnected to MongoDB Atlas\nPathError [TypeError]: Missing parameter name at index 1: *; visit https://git.new/pathToRegexpError for info\n    at name (/var/task/backend/node_modules/path-to-regexp/dist/index.js:96:19)\n    at parse (/var/task/backend/node_modules/path-to-regexp/dist/index.js:113:68)\n    at pathToRegexp (/var/task/backend/node_modules/path-to-regexp/dist/index.js:267:58)\n    at Object.match (/var/task/backend/node_modules/path-to-regexp/dist/index.js:237:30)\n    at matcher (/var/task/backend/node_modules/router/lib/layer.js:86:23)\n    at new Layer (/var/task/backend/node_modules/router/lib/layer.js:93:62)\n    at Function.route (/var/task/backend/node_modules/router/index.js:428:17)\n    at Function.route (/var/task/backend/node_modules/express/lib/application.js:257:22)\n    at app.<computed> [as get] (/var/task/backend/node_modules/express/lib/application.js:478:22)\n    at Object.<anonymous> (/var/task/backend/server.js:124:9) {\n  originalPath: '*'\n}\nNode.js process exited with exit status: 1. The logs above can help with debugging the issue.","projectId":"prj_uRMIndd7p1kBQ5otSkgRpD3RLMnU","traceId":"","sessionId":"","invocationId":"01K9CSNW21YG4XE58WE3E7STZ4","instanceId":"","concurrency":-1},{"TimeUTC":"2025-11-06 14:38:37","timestampInMs":1762439917633,"requestPath":"multi-college-data-collection-system-9cwyx1q63.vercel.app/favicon.png","requestMethod":"GET","requestQueryString":"","responseStatusCode":500,"requestId":"lfzld-1762439917580-2906afa814a6","requestUserAgent":"vercel-favicon/1.0","level":"error","environment":"production","branch":"main","vercelCache":"","type":"lambda","function":"/server.js","host":"multi-college-data-collection-system-9cwyx1q63.vercel.app","deploymentDomain":"multi-college-data-collection-system-9cwyx1q63.vercel.app","deploymentId":"dpl_DXTZ13sYdb3DTyjZDb72UcQsc5rU","durationMs":1258,"region":"iad1","maxMemoryUsed":161,"memorySize":2048,"message":"","projectId":"prj_uRMIndd7p1kBQ5otSkgRpD3RLMnU","traceId":"","sessionId":"","invocationId":"01K9CSNW21YG4XE58WE3E7STZ4","instanceId":"","concurrency":1},{"TimeUTC":"2025-11-06 14:38:37","timestampInMs":1762439917536,"requestPath":"multi-college-data-collection-system-9cwyx1q63.vercel.app/favicon.ico","requestMethod":"GET","requestQueryString":"","responseStatusCode":-1,"requestId":"brrqm-1762439916153-f766a39147e6","requestUserAgent":"vercel-favicon/1.0","level":"error","environment":"production","branch":"main","vercelCache":"","type":"lambda","function":"/server.js","host":"multi-college-data-collection-system-9cwyx1q63.vercel.app","deploymentDomain":"multi-college-data-collection-system-9cwyx1q63.vercel.app","deploymentId":"dpl_DXTZ13sYdb3DTyjZDb72UcQsc5rU","durationMs":-1,"region":"iad1","maxMemoryUsed":-1,"memorySize":-1,"message":"[dotenv@17.2.2] injecting env (0) from .env -- tip: ⚙️  suppress all logs with { quiet: true }\n(node:4) [MONGODB DRIVER] Warning: useNewUrlParser is a deprecated option: useNewUrlParser has no effect since Node.js Driver version 4.0.0 and will be removed in the next major version\n(Use `node --trace-warnings ...` to show where the warning was created)\n(node:4) [MONGODB DRIVER] Warning: useUnifiedTopology is a deprecated option: useUnifiedTopology has no effect since Node.js Driver version 4.0.0 and will be removed in the next major version\n[dotenv@17.2.2] injecting env (0) from .env -- tip: ⚙️  suppress all logs with { quiet: true }\nConnected to MongoDB Atlas\nPathError [TypeError]: Missing parameter name at index 1: *; visit https://git.new/pathToRegexpError for info\n    at name (/var/task/backend/node_modules/path-to-regexp/dist/index.js:96:19)\n    at parse (/var/task/backend/node_modules/path-to-regexp/dist/index.js:113:68)\n    at pathToRegexp (/var/task/backend/node_modules/path-to-regexp/dist/index.js:267:58)\n    at Object.match (/var/task/backend/node_modules/path-to-regexp/dist/index.js:237:30)\n    at matcher (/var/task/backend/node_modules/router/lib/layer.js:86:23)\n    at new Layer (/var/task/backend/node_modules/router/lib/layer.js:93:62)\n    at Function.route (/var/task/backend/node_modules/router/index.js:428:17)\n    at Function.route (/var/task/backend/node_modules/express/lib/application.js:257:22)\n    at app.<computed> [as get] (/var/task/backend/node_modules/express/lib/application.js:478:22)\n    at Object.<anonymous> (/var/task/backend/server.js:124:9) {\n  originalPath: '*'\n}\nNode.js process exited with exit status: 1. The logs above can help with debugging the issue.","projectId":"prj_uRMIndd7p1kBQ5otSkgRpD3RLMnU","traceId":"","sessionId":"","invocationId":"01K9CSNTNMN8FDTSH702WV3DGY","instanceId":"","concurrency":-1},{"TimeUTC":"2025-11-06 14:38:36","timestampInMs":1762439916212,"requestPath":"multi-college-data-collection-system-9cwyx1q63.vercel.app/favicon.ico","requestMethod":"GET","requestQueryString":"","responseStatusCode":500,"requestId":"brrqm-1762439916153-f766a39147e6","requestUserAgent":"vercel-favicon/1.0","level":"error","environment":"production","branch":"main","vercelCache":"","type":"lambda","function":"/server.js","host":"multi-college-data-collection-system-9cwyx1q63.vercel.app","deploymentDomain":"multi-college-data-collection-system-9cwyx1q63.vercel.app","deploymentId":"dpl_DXTZ13sYdb3DTyjZDb72UcQsc5rU","durationMs":1305,"region":"iad1","maxMemoryUsed":162,"memorySize":2048,"message":"","projectId":"prj_uRMIndd7p1kBQ5otSkgRpD3RLMnU","traceId":"","sessionId":"","invocationId":"01K9CSNTNMN8FDTSH702WV3DGY","instanceId":"","concurrency":1},{"TimeUTC":"2025-11-06 14:38:34","timestampInMs":1762439914027,"requestPath":"multi-college-data-collection-system-9cwyx1q63.vercel.app/favicon.ico","requestMethod":"GET","requestQueryString":"","responseStatusCode":-1,"requestId":"xhpsp-1762439912711-4f2c46e1cbd1","requestUserAgent":"vercel-favicon/1.0","level":"error","environment":"production","branch":"main","vercelCache":"","type":"lambda","function":"/server.js","host":"multi-college-data-collection-system-9cwyx1q63.vercel.app","deploymentDomain":"multi-college-data-collection-system-9cwyx1q63.vercel.app","deploymentId":"dpl_DXTZ13sYdb3DTyjZDb72UcQsc5rU","durationMs":-1,"region":"iad1","maxMemoryUsed":-1,"memorySize":-1,"message":"[dotenv@17.2.2] injecting env (0) from .env -- tip: ⚙️  write to custom object with { processEnv: myObject }\n(node:4) [MONGODB DRIVER] Warning: useNewUrlParser is a deprecated option: useNewUrlParser has no effect since Node.js Driver version 4.0.0 and will be removed in the next major version\n(Use `node --trace-warnings ...` to show where the warning was created)\n(node:4) [MONGODB DRIVER] Warning: useUnifiedTopology is a deprecated option: useUnifiedTopology has no effect since Node.js Driver version 4.0.0 and will be removed in the next major version\n[dotenv@17.2.2] injecting env (0) from .env -- tip: 🔐 prevent building .env in docker: https://dotenvx.com/prebuild\nConnected to MongoDB Atlas\nPathError [TypeError]: Missing parameter name at index 1: *; visit https://git.new/pathToRegexpError for info\n    at name (/var/task/backend/node_modules/path-to-regexp/dist/index.js:96:19)\n    at parse (/var/task/backend/node_modules/path-to-regexp/dist/index.js:113:68)\n    at pathToRegexp (/var/task/backend/node_modules/path-to-regexp/dist/index.js:267:58)\n    at Object.match (/var/task/backend/node_modules/path-to-regexp/dist/index.js:237:30)\n    at matcher (/var/task/backend/node_modules/router/lib/layer.js:86:23)\n    at new Layer (/var/task/backend/node_modules/router/lib/layer.js:93:62)\n    at Function.route (/var/task/backend/node_modules/router/index.js:428:17)\n    at Function.route (/var/task/backend/node_modules/express/lib/application.js:257:22)\n    at app.<computed> [as get] (/var/task/backend/node_modules/express/lib/application.js:478:22)\n    at Object.<anonymous> (/var/task/backend/server.js:124:9) {\n  originalPath: '*'\n}\nNode.js process exited with exit status: 1. The logs above can help with debugging the issue.","projectId":"prj_uRMIndd7p1kBQ5otSkgRpD3RLMnU","traceId":"","sessionId":"","invocationId":"01K9CSNQA0E5PR132NJBTA3DKS","instanceId":"","concurrency":-1},{"TimeUTC":"2025-11-06 14:38:32","timestampInMs":1762439912768,"requestPath":"multi-college-data-collection-system-9cwyx1q63.vercel.app/favicon.ico","requestMethod":"GET","requestQueryString":"","responseStatusCode":500,"requestId":"xhpsp-1762439912711-4f2c46e1cbd1","requestUserAgent":"vercel-favicon/1.0","level":"error","environment":"production","branch":"main","vercelCache":"","type":"lambda","function":"/server.js","host":"multi-college-data-collection-system-9cwyx1q63.vercel.app","deploymentDomain":"multi-college-data-collection-system-9cwyx1q63.vercel.app","deploymentId":"dpl_DXTZ13sYdb3DTyjZDb72UcQsc5rU","durationMs":1245,"region":"iad1","maxMemoryUsed":164,"memorySize":2048,"message":"","projectId":"prj_uRMIndd7p1kBQ5otSkgRpD3RLMnU","traceId":"","sessionId":"","invocationId":"01K9CSNQA0E5PR132NJBTA3DKS","instanceId":"","concurrency":1},{"TimeUTC":"2025-11-06 14:38:31","timestampInMs":1762439911623,"requestPath":"multi-college-data-collection-system-9cwyx1q63.vercel.app/favicon.ico","requestMethod":"GET","requestQueryString":"","responseStatusCode":-1,"requestId":"mpfs6-1762439910235-1a6e30b70ce2","requestUserAgent":"vercel-favicon/1.0","level":"error","environment":"production","branch":"main","vercelCache":"","type":"lambda","function":"/server.js","host":"multi-college-data-collection-system-9cwyx1q63.vercel.app","deploymentDomain":"multi-college-data-collection-system-9cwyx1q63.vercel.app","deploymentId":"dpl_DXTZ13sYdb3DTyjZDb72UcQsc5rU","durationMs":-1,"region":"iad1","maxMemoryUsed":-1,"memorySize":-1,"message":"[dotenv@17.2.2] injecting env (0) from .env -- tip: 🔐 prevent committing .env to code: https://dotenvx.com/precommit\n(node:4) [MONGODB DRIVER] Warning: useNewUrlParser is a deprecated option: useNewUrlParser has no effect since Node.js Driver version 4.0.0 and will be removed in the next major version\n(Use `node --trace-warnings ...` to show where the warning was created)\n(node:4) [MONGODB DRIVER] Warning: useUnifiedTopology is a deprecated option: useUnifiedTopology has no effect since Node.js Driver version 4.0.0 and will be removed in the next major version\n[dotenv@17.2.2] injecting env (0) from .env -- tip: 📡 observe env with Radar: https://dotenvx.com/radar\nConnected to MongoDB Atlas\nPathError [TypeError]: Missing parameter name at index 1: *; visit https://git.new/pathToRegexpError for info\n    at name (/var/task/backend/node_modules/path-to-regexp/dist/index.js:96:19)\n    at parse (/var/task/backend/node_modules/path-to-regexp/dist/index.js:113:68)\n    at pathToRegexp (/var/task/backend/node_modules/path-to-regexp/dist/index.js:267:58)\n    at Object.match (/var/task/backend/node_modules/path-to-regexp/dist/index.js:237:30)\n    at matcher (/var/task/backend/node_modules/router/lib/layer.js:86:23)\n    at new Layer (/var/task/backend/node_modules/router/lib/layer.js:93:62)\n    at Function.route (/var/task/backend/node_modules/router/index.js:428:17)\n    at Function.route (/var/task/backend/node_modules/express/lib/application.js:257:22)\n    at app.<computed> [as get] (/var/task/backend/node_modules/express/lib/application.js:478:22)\n    at Object.<anonymous> (/var/task/backend/server.js:124:9) {\n  originalPath: '*'\n}\nNode.js process exited with exit status: 1. The logs above can help with debugging the issue.","projectId":"prj_uRMIndd7p1kBQ5otSkgRpD3RLMnU","traceId":"","sessionId":"","invocationId":"01K9CSNMZC5995MBF5F8TM8K24","instanceId":"","concurrency":-1},{"TimeUTC":"2025-11-06 14:38:30","timestampInMs":1762439910380,"requestPath":"multi-college-data-collection-system-9cwyx1q63.vercel.app/favicon.ico","requestMethod":"GET","requestQueryString":"","responseStatusCode":500,"requestId":"mpfs6-1762439910235-1a6e30b70ce2","requestUserAgent":"vercel-favicon/1.0","level":"error","environment":"production","branch":"main","vercelCache":"","type":"lambda","function":"/server.js","host":"multi-college-data-collection-system-9cwyx1q63.vercel.app","deploymentDomain":"multi-college-data-collection-system-9cwyx1q63.vercel.app","deploymentId":"dpl_DXTZ13sYdb3DTyjZDb72UcQsc5rU","durationMs":1229,"region":"iad1","maxMemoryUsed":163,"memorySize":2048,"message":"","projectId":"prj_uRMIndd7p1kBQ5otSkgRpD3RLMnU","traceId":"","sessionId":"","invocationId":"01K9CSNMZC5995MBF5F8TM8K24","instanceId":"","concurrency":1},{"TimeUTC":"2025-11-06 14:38:30","timestampInMs":1762439910120,"requestPath":"multi-college-data-collection-system-9cwyx1q63.vercel.app/","requestMethod":"GET","requestQueryString":"","responseStatusCode":-1,"requestId":"22fl2-1762439908694-c0a975bba15a","requestUserAgent":"vercel-favicon/1.0","level":"error","environment":"production","branch":"main","vercelCache":"","type":"lambda","function":"/server.js","host":"multi-college-data-collection-system-9cwyx1q63.vercel.app","deploymentDomain":"multi-college-data-collection-system-9cwyx1q63.vercel.app","deploymentId":"dpl_DXTZ13sYdb3DTyjZDb72UcQsc5rU","durationMs":-1,"region":"iad1","maxMemoryUsed":-1,"memorySize":-1,"message":"[dotenv@17.2.2] injecting env (0) from .env -- tip: ⚙️  specify custom .env file path with { path: '/custom/path/.env' }\n(node:4) [MONGODB DRIVER] Warning: useNewUrlParser is a deprecated option: useNewUrlParser has no effect since Node.js Driver version 4.0.0 and will be removed in the next major version\n(Use `node --trace-warnings ...` to show where the warning was created)\n(node:4) [MONGODB DRIVER] Warning: useUnifiedTopology is a deprecated option: useUnifiedTopology has no effect since Node.js Driver version 4.0.0 and will be removed in the next major version\n[dotenv@17.2.2] injecting env (0) from .env -- tip: 🔐 prevent committing .env to code: https://dotenvx.com/precommit\nConnected to MongoDB Atlas\nPathError [TypeError]: Missing parameter name at index 1: *; visit https://git.new/pathToRegexpError for info\n    at name (/var/task/backend/node_modules/path-to-regexp/dist/index.js:96:19)\n    at parse (/var/task/backend/node_modules/path-to-regexp/dist/index.js:113:68)\n    at pathToRegexp (/var/task/backend/node_modules/path-to-regexp/dist/index.js:267:58)\n    at Object.match (/var/task/backend/node_modules/path-to-regexp/dist/index.js:237:30)\n    at matcher (/var/task/backend/node_modules/router/lib/layer.js:86:23)\n    at new Layer (/var/task/backend/node_modules/router/lib/layer.js:93:62)\n    at Function.route (/var/task/backend/node_modules/router/index.js:428:17)\n    at Function.route (/var/task/backend/node_modules/express/lib/application.js:257:22)\n    at app.<computed> [as get] (/var/task/backend/node_modules/express/lib/application.js:478:22)\n    at Object.<anonymous> (/var/task/backend/server.js:124:9) {\n  originalPath: '*'\n}\nNode.js process exited with exit status: 1. The logs above can help with debugging the issue.","projectId":"prj_uRMIndd7p1kBQ5otSkgRpD3RLMnU","traceId":"","sessionId":"","invocationId":"01K9CSNKG9YFW9B4HS82DZ1KF6","instanceId":"","concurrency":-1},{"TimeUTC":"2025-11-06 14:38:28","timestampInMs":1762439908873,"requestPath":"multi-college-data-collection-system-9cwyx1q63.vercel.app/","requestMethod":"GET","requestQueryString":"","responseStatusCode":500,"requestId":"22fl2-1762439908694-c0a975bba15a","requestUserAgent":"vercel-favicon/1.0","level":"error","environment":"production","branch":"main","vercelCache":"","type":"lambda","function":"/server.js","host":"multi-college-data-collection-system-9cwyx1q63.vercel.app","deploymentDomain":"multi-college-data-collection-system-9cwyx1q63.vercel.app","deploymentId":"dpl_DXTZ13sYdb3DTyjZDb72UcQsc5rU","durationMs":1232,"region":"iad1","maxMemoryUsed":162,"memorySize":2048,"message":"","projectId":"prj_uRMIndd7p1kBQ5otSkgRpD3RLMnU","traceId":"","sessionId":"","invocationId":"01K9CSNKG9YFW9B4HS82DZ1KF6","instanceId":"","concurrency":1},{"TimeUTC":"2025-11-06 14:38:27","timestampInMs":1762439907590,"requestPath":"multi-college-data-collection-system-9cwyx1q63.vercel.app/","requestMethod":"GET","requestQueryString":"","responseStatusCode":-1,"requestId":"8p92w-1762439906247-78b2ff54d6b9","requestUserAgent":"vercel-favicon/1.0","level":"error","environment":"production","branch":"main","vercelCache":"","type":"lambda","function":"/server.js","host":"multi-college-data-collection-system-9cwyx1q63.vercel.app","deploymentDomain":"multi-college-data-collection-system-9cwyx1q63.vercel.app","deploymentId":"dpl_DXTZ13sYdb3DTyjZDb72UcQsc5rU","durationMs":-1,"region":"iad1","maxMemoryUsed":-1,"memorySize":-1,"message":"[dotenv@17.2.2] injecting env (0) from .env -- tip: ⚙️  specify custom .env file path with { path: '/custom/path/.env' }\n(node:4) [MONGODB DRIVER] Warning: useNewUrlParser is a deprecated option: useNewUrlParser has no effect since Node.js Driver version 4.0.0 and will be removed in the next major version\n(Use `node --trace-warnings ...` to show where the warning was created)\n(node:4) [MONGODB DRIVER] Warning: useUnifiedTopology is a deprecated option: useUnifiedTopology has no effect since Node.js Driver version 4.0.0 and will be removed in the next major version\n[dotenv@17.2.2] injecting env (0) from .env -- tip: ⚙️  override existing env vars with { override: true }\nConnected to MongoDB Atlas\nPathError [TypeError]: Missing parameter name at index 1: *; visit https://git.new/pathToRegexpError for info\n    at name (/var/task/backend/node_modules/path-to-regexp/dist/index.js:96:19)\n    at parse (/var/task/backend/node_modules/path-to-regexp/dist/index.js:113:68)\n    at pathToRegexp (/var/task/backend/node_modules/path-to-regexp/dist/index.js:267:58)\n    at Object.match (/var/task/backend/node_modules/path-to-regexp/dist/index.js:237:30)\n    at matcher (/var/task/backend/node_modules/router/lib/layer.js:86:23)\n    at new Layer (/var/task/backend/node_modules/router/lib/layer.js:93:62)\n    at Function.route (/var/task/backend/node_modules/router/index.js:428:17)\n    at Function.route (/var/task/backend/node_modules/express/lib/application.js:257:22)\n    at app.<computed> [as get] (/var/task/backend/node_modules/express/lib/application.js:478:22)\n    at Object.<anonymous> (/var/task/backend/server.js:124:9) {\n  originalPath: '*'\n}\nNode.js process exited with exit status: 1. The logs above can help with debugging the issue.","projectId":"prj_uRMIndd7p1kBQ5otSkgRpD3RLMnU","traceId":"","sessionId":"","invocationId":"01K9CSNGZVWJHWTFF5HBKGB1K5","instanceId":"","concurrency":-1},{"TimeUTC":"2025-11-06 14:38:26","timestampInMs":1762439906299,"requestPath":"multi-college-data-collection-system-9cwyx1q63.vercel.app/","requestMethod":"GET","requestQueryString":"","responseStatusCode":500,"requestId":"8p92w-1762439906247-78b2ff54d6b9","requestUserAgent":"vercel-favicon/1.0","level":"error","environment":"production","branch":"main","vercelCache":"","type":"lambda","function":"/server.js","host":"multi-college-data-collection-system-9cwyx1q63.vercel.app","deploymentDomain":"multi-college-data-collection-system-9cwyx1q63.vercel.app","deploymentId":"dpl_DXTZ13sYdb3DTyjZDb72UcQsc5rU","durationMs":1274,"region":"iad1","maxMemoryUsed":162,"memorySize":2048,"message":"","projectId":"prj_uRMIndd7p1kBQ5otSkgRpD3RLMnU","traceId":"","sessionId":"","invocationId":"01K9CSNGZVWJHWTFF5HBKGB1K5","instanceId":"","concurrency":1},{"TimeUTC":"2025-11-06 14:38:20","timestampInMs":1762439900341,"requestPath":"multi-college-data-collection-system-9cwyx1q63.vercel.app/favicon.ico","requestMethod":"GET","requestQueryString":"","responseStatusCode":-1,"requestId":"wbpgw-1762439898710-453303da2793","requestUserAgent":"vercel-screenshot/1.0","level":"error","environment":"production","branch":"main","vercelCache":"","type":"lambda","function":"/server.js","host":"multi-college-data-collection-system-9cwyx1q63.vercel.app","deploymentDomain":"multi-college-data-collection-system-9cwyx1q63.vercel.app","deploymentId":"dpl_DXTZ13sYdb3DTyjZDb72UcQsc5rU","durationMs":-1,"region":"iad1","maxMemoryUsed":-1,"memorySize":-1,"message":"[dotenv@17.2.2] injecting env (0) from .env -- tip: ⚙️  write to custom object with { processEnv: myObject }\n(node:4) [MONGODB DRIVER] Warning: useNewUrlParser is a deprecated option: useNewUrlParser has no effect since Node.js Driver version 4.0.0 and will be removed in the next major version\n(Use `node --trace-warnings ...` to show where the warning was created)\n(node:4) [MONGODB DRIVER] Warning: useUnifiedTopology is a deprecated option: useUnifiedTopology has no effect since Node.js Driver version 4.0.0 and will be removed in the next major version\n[dotenv@17.2.2] injecting env (0) from .env -- tip: ⚙️  write to custom object with { processEnv: myObject }\nConnected to MongoDB Atlas\nPathError [TypeError]: Missing parameter name at index 1: *; visit https://git.new/pathToRegexpError for info\n    at name (/var/task/backend/node_modules/path-to-regexp/dist/index.js:96:19)\n    at parse (/var/task/backend/node_modules/path-to-regexp/dist/index.js:113:68)\n    at pathToRegexp (/var/task/backend/node_modules/path-to-regexp/dist/index.js:267:58)\n    at Object.match (/var/task/backend/node_modules/path-to-regexp/dist/index.js:237:30)\n    at matcher (/var/task/backend/node_modules/router/lib/layer.js:86:23)\n    at new Layer (/var/task/backend/node_modules/router/lib/layer.js:93:62)\n    at Function.route (/var/task/backend/node_modules/router/index.js:428:17)\n    at Function.route (/var/task/backend/node_modules/express/lib/application.js:257:22)\n    at app.<computed> [as get] (/var/task/backend/node_modules/express/lib/application.js:478:22)\n    at Object.<anonymous> (/var/task/backend/server.js:124:9) {\n  originalPath: '*'\n}\nNode.js process exited with exit status: 1. The logs above can help with debugging the issue.","projectId":"prj_uRMIndd7p1kBQ5otSkgRpD3RLMnU","traceId":"","sessionId":"","invocationId":"01K9CSN9XD830MHTYRAH41PD6N","instanceId":"","concurrency":-1},{"TimeUTC":"2025-11-06 14:38:19","timestampInMs":1762439899665,"requestPath":"multi-college-data-collection-system-9cwyx1q63.vercel.app/favicon.ico","requestMethod":"GET","requestQueryString":"","responseStatusCode":-1,"requestId":"g82bl-1762439898404-ba18fe7d24b7","requestUserAgent":"vercel-screenshot/1.0","level":"error","environment":"production","branch":"main","vercelCache":"","type":"lambda","function":"/server.js","host":"multi-college-data-collection-system-9cwyx1q63.vercel.app","deploymentDomain":"multi-college-data-collection-system-9cwyx1q63.vercel.app","deploymentId":"dpl_DXTZ13sYdb3DTyjZDb72UcQsc5rU","durationMs":-1,"region":"iad1","maxMemoryUsed":-1,"memorySize":-1,"message":"[dotenv@17.2.2] injecting env (0) from .env -- tip: 🔐 encrypt with Dotenvx: https://dotenvx.com\n(node:4) [MONGODB DRIVER] Warning: useNewUrlParser is a deprecated option: useNewUrlParser has no effect since Node.js Driver version 4.0.0 and will be removed in the next major version\n(Use `node --trace-warnings ...` to show where the warning was created)\n(node:4) [MONGODB DRIVER] Warning: useUnifiedTopology is a deprecated option: useUnifiedTopology has no effect since Node.js Driver version 4.0.0 and will be removed in the next major version\n[dotenv@17.2.2] injecting env (0) from .env -- tip: 🔐 prevent building .env in docker: https://dotenvx.com/prebuild\nConnected to MongoDB Atlas\nPathError [TypeError]: Missing parameter name at index 1: *; visit https://git.new/pathToRegexpError for info\n    at name (/var/task/backend/node_modules/path-to-regexp/dist/index.js:96:19)\n    at parse (/var/task/backend/node_modules/path-to-regexp/dist/index.js:113:68)\n    at pathToRegexp (/var/task/backend/node_modules/path-to-regexp/dist/index.js:267:58)\n    at Object.match (/var/task/backend/node_modules/path-to-regexp/dist/index.js:237:30)\n    at matcher (/var/task/backend/node_modules/router/lib/layer.js:86:23)\n    at new Layer (/var/task/backend/node_modules/router/lib/layer.js:93:62)\n    at Function.route (/var/task/backend/node_modules/router/index.js:428:17)\n    at Function.route (/var/task/backend/node_modules/express/lib/application.js:257:22)\n    at app.<computed> [as get] (/var/task/backend/node_modules/express/lib/application.js:478:22)\n    at Object.<anonymous> (/var/task/backend/server.js:124:9) {\n  originalPath: '*'\n}\nNode.js process exited with exit status: 1. The logs above can help with debugging the issue.","projectId":"prj_uRMIndd7p1kBQ5otSkgRpD3RLMnU","traceId":"","sessionId":"","invocationId":"01K9CSN9AD5AYPAZJJ7E2Q4FAR","instanceId":"","concurrency":-1},{"TimeUTC":"2025-11-06 14:38:19","timestampInMs":1762439899053,"requestPath":"multi-college-data-collection-system-9cwyx1q63.vercel.app/favicon.ico","requestMethod":"GET","requestQueryString":"","responseStatusCode":500,"requestId":"wbpgw-1762439898710-453303da2793","requestUserAgent":"vercel-screenshot/1.0","level":"error","environment":"production","branch":"main","vercelCache":"","type":"lambda","function":"/server.js","host":"multi-college-data-collection-system-9cwyx1q63.vercel.app","deploymentDomain":"multi-college-data-collection-system-9cwyx1q63.vercel.app","deploymentId":"dpl_DXTZ13sYdb3DTyjZDb72UcQsc5rU","durationMs":1274,"region":"iad1","maxMemoryUsed":161,"memorySize":2048,"message":"","projectId":"prj_uRMIndd7p1kBQ5otSkgRpD3RLMnU","traceId":"","sessionId":"","invocationId":"01K9CSN9XD830MHTYRAH41PD6N","instanceId":"","concurrency":1},{"TimeUTC":"2025-11-06 14:38:18","timestampInMs":1762439898604,"requestPath":"multi-college-data-collection-system-9cwyx1q63.vercel.app/","requestMethod":"GET","requestQueryString":"","responseStatusCode":-1,"requestId":"l2n8k-1762439897167-d56deb5fe0e9","requestUserAgent":"vercel-screenshot/1.0","level":"error","environment":"production","branch":"main","vercelCache":"","type":"lambda","function":"/server.js","host":"multi-college-data-collection-system-9cwyx1q63.vercel.app","deploymentDomain":"multi-college-data-collection-system-9cwyx1q63.vercel.app","deploymentId":"dpl_DXTZ13sYdb3DTyjZDb72UcQsc5rU","durationMs":-1,"region":"iad1","maxMemoryUsed":-1,"memorySize":-1,"message":"[dotenv@17.2.2] injecting env (0) from .env -- tip: 📡 observe env with Radar: https://dotenvx.com/radar\n(node:4) [MONGODB DRIVER] Warning: useNewUrlParser is a deprecated option: useNewUrlParser has no effect since Node.js Driver version 4.0.0 and will be removed in the next major version\n(Use `node --trace-warnings ...` to show where the warning was created)\n(node:4) [MONGODB DRIVER] Warning: useUnifiedTopology is a deprecated option: useUnifiedTopology has no effect since Node.js Driver version 4.0.0 and will be removed in the next major version\n[dotenv@17.2.2] injecting env (0) from .env -- tip: ⚙️  enable debug logging with { debug: true }\nConnected to MongoDB Atlas\nPathError [TypeError]: Missing parameter name at index 1: *; visit https://git.new/pathToRegexpError for info\n    at name (/var/task/backend/node_modules/path-to-regexp/dist/index.js:96:19)\n    at parse (/var/task/backend/node_modules/path-to-regexp/dist/index.js:113:68)\n    at pathToRegexp (/var/task/backend/node_modules/path-to-regexp/dist/index.js:267:58)\n    at Object.match (/var/task/backend/node_modules/path-to-regexp/dist/index.js:237:30)\n    at matcher (/var/task/backend/node_modules/router/lib/layer.js:86:23)\n    at new Layer (/var/task/backend/node_modules/router/lib/layer.js:93:62)\n    at Function.route (/var/task/backend/node_modules/router/index.js:428:17)\n    at Function.route (/var/task/backend/node_modules/express/lib/application.js:257:22)\n    at app.<computed> [as get] (/var/task/backend/node_modules/express/lib/application.js:478:22)\n    at Object.<anonymous> (/var/task/backend/server.js:124:9) {\n  originalPath: '*'\n}\nNode.js process exited with exit status: 1. The logs above can help with debugging the issue.","projectId":"prj_uRMIndd7p1kBQ5otSkgRpD3RLMnU","traceId":"","sessionId":"","invocationId":"01K9CSN86TT56AWC8YAGJAVG5K","instanceId":"","concurrency":-1},{"TimeUTC":"2025-11-06 14:38:18","timestampInMs":1762439898445,"requestPath":"multi-college-data-collection-system-9cwyx1q63.vercel.app/favicon.ico","requestMethod":"GET","requestQueryString":"","responseStatusCode":500,"requestId":"g82bl-1762439898404-ba18fe7d24b7","requestUserAgent":"vercel-screenshot/1.0","level":"error","environment":"production","branch":"main","vercelCache":"","type":"lambda","function":"/server.js","host":"multi-college-data-collection-system-9cwyx1q63.vercel.app","deploymentDomain":"multi-college-data-collection-system-9cwyx1q63.vercel.app","deploymentId":"dpl_DXTZ13sYdb3DTyjZDb72UcQsc5rU","durationMs":1205,"region":"iad1","maxMemoryUsed":164,"memorySize":2048,"message":"","projectId":"prj_uRMIndd7p1kBQ5otSkgRpD3RLMnU","traceId":"","sessionId":"","invocationId":"01K9CSN9AD5AYPAZJJ7E2Q4FAR","instanceId":"","concurrency":1},{"TimeUTC":"2025-11-06 14:38:18","timestampInMs":1762439898235,"requestPath":"multi-college-data-collection-system-9cwyx1q63.vercel.app/","requestMethod":"GET","requestQueryString":"","responseStatusCode":-1,"requestId":"22fl2-1762439896833-13460c82ff12","requestUserAgent":"vercel-screenshot/1.0","level":"error","environment":"production","branch":"main","vercelCache":"","type":"lambda","function":"/server.js","host":"multi-college-data-collection-system-9cwyx1q63.vercel.app","deploymentDomain":"multi-college-data-collection-system-9cwyx1q63.vercel.app","deploymentId":"dpl_DXTZ13sYdb3DTyjZDb72UcQsc5rU","durationMs":-1,"region":"iad1","maxMemoryUsed":-1,"memorySize":-1,"message":"[dotenv@17.2.2] injecting env (0) from .env -- tip: 🔐 encrypt with Dotenvx: https://dotenvx.com\n(node:4) [MONGODB DRIVER] Warning: useNewUrlParser is a deprecated option: useNewUrlParser has no effect since Node.js Driver version 4.0.0 and will be removed in the next major version\n(Use `node --trace-warnings ...` to show where the warning was created)\n(node:4) [MONGODB DRIVER] Warning: useUnifiedTopology is a deprecated option: useUnifiedTopology has no effect since Node.js Driver version 4.0.0 and will be removed in the next major version\n[dotenv@17.2.2] injecting env (0) from .env -- tip: 📡 version env with Radar: https://dotenvx.com/radar\nConnected to MongoDB Atlas\nPathError [TypeError]: Missing parameter name at index 1: *; visit https://git.new/pathToRegexpError for info\n    at name (/var/task/backend/node_modules/path-to-regexp/dist/index.js:96:19)\n    at parse (/var/task/backend/node_modules/path-to-regexp/dist/index.js:113:68)\n    at pathToRegexp (/var/task/backend/node_modules/path-to-regexp/dist/index.js:267:58)\n    at Object.match (/var/task/backend/node_modules/path-to-regexp/dist/index.js:237:30)\n    at matcher (/var/task/backend/node_modules/router/lib/layer.js:86:23)\n    at new Layer (/var/task/backend/node_modules/router/lib/layer.js:93:62)\n    at Function.route (/var/task/backend/node_modules/router/index.js:428:17)\n    at Function.route (/var/task/backend/node_modules/express/lib/application.js:257:22)\n    at app.<computed> [as get] (/var/task/backend/node_modules/express/lib/application.js:478:22)\n    at Object.<anonymous> (/var/task/backend/server.js:124:9) {\n  originalPath: '*'\n}\nNode.js process exited with exit status: 1. The logs above can help with debugging the issue.","projectId":"prj_uRMIndd7p1kBQ5otSkgRpD3RLMnU","traceId":"","sessionId":"","invocationId":"01K9CSN7XWB00ZE26VB38YDZ81","instanceId":"","concurrency":-1},{"TimeUTC":"2025-11-06 14:38:17","timestampInMs":1762439897306,"requestPath":"multi-college-data-collection-system-9cwyx1q63.vercel.app/","requestMethod":"GET","requestQueryString":"","responseStatusCode":500,"requestId":"l2n8k-1762439897167-d56deb5fe0e9","requestUserAgent":"vercel-screenshot/1.0","level":"error","environment":"production","branch":"main","vercelCache":"","type":"lambda","function":"/server.js","host":"multi-college-data-collection-system-9cwyx1q63.vercel.app","deploymentDomain":"multi-college-data-collection-system-9cwyx1q63.vercel.app","deploymentId":"dpl_DXTZ13sYdb3DTyjZDb72UcQsc5rU","durationMs":1274,"region":"iad1","maxMemoryUsed":161,"memorySize":2048,"message":"","projectId":"prj_uRMIndd7p1kBQ5otSkgRpD3RLMnU","traceId":"","sessionId":"","invocationId":"01K9CSN86TT56AWC8YAGJAVG5K","instanceId":"","concurrency":1},{"TimeUTC":"2025-11-06 14:38:17","timestampInMs":1762439897052,"requestPath":"multi-college-data-collection-system-9cwyx1q63.vercel.app/","requestMethod":"GET","requestQueryString":"","responseStatusCode":-1,"requestId":"jv7vr-1762439893705-4eaa8b5f58ab","requestUserAgent":"vercel-screenshot/1.0","level":"error","environment":"production","branch":"main","vercelCache":"","type":"lambda","function":"/server.js","host":"multi-college-data-collection-system-9cwyx1q63.vercel.app","deploymentDomain":"multi-college-data-collection-system-9cwyx1q63.vercel.app","deploymentId":"dpl_DXTZ13sYdb3DTyjZDb72UcQsc5rU","durationMs":-1,"region":"iad1","maxMemoryUsed":-1,"memorySize":-1,"message":"[dotenv@17.2.2] injecting env (0) from .env -- tip: 🛠️  run anywhere with `dotenvx run -- yourcommand`\n(node:4) [MONGODB DRIVER] Warning: useNewUrlParser is a deprecated option: useNewUrlParser has no effect since Node.js Driver version 4.0.0 and will be removed in the next major version\n(Use `node --trace-warnings ...` to show where the warning was created)\n(node:4) [MONGODB DRIVER] Warning: useUnifiedTopology is a deprecated option: useUnifiedTopology has no effect since Node.js Driver version 4.0.0 and will be removed in the next major version\n[dotenv@17.2.2] injecting env (0) from .env -- tip: ⚙️  write to custom object with { processEnv: myObject }\nConnected to MongoDB Atlas\nPathError [TypeError]: Missing parameter name at index 1: *; visit https://git.new/pathToRegexpError for info\n    at name (/var/task/backend/node_modules/path-to-regexp/dist/index.js:96:19)\n    at parse (/var/task/backend/node_modules/path-to-regexp/dist/index.js:113:68)\n    at pathToRegexp (/var/task/backend/node_modules/path-to-regexp/dist/index.js:267:58)\n    at Object.match (/var/task/backend/node_modules/path-to-regexp/dist/index.js:237:30)\n    at matcher (/var/task/backend/node_modules/router/lib/layer.js:86:23)\n    at new Layer (/var/task/backend/node_modules/router/lib/layer.js:93:62)\n    at Function.route (/var/task/backend/node_modules/router/index.js:428:17)\n    at Function.route (/var/task/backend/node_modules/express/lib/application.js:257:22)\n    at app.<computed> [as get] (/var/task/backend/node_modules/express/lib/application.js:478:22)\n    at Object.<anonymous> (/var/task/backend/server.js:124:9) {\n  originalPath: '*'\n}\nNode.js process exited with exit status: 1. The logs above can help with debugging the issue.\n[dotenv@17.2.2] injecting env (0) from .env -- tip: ⚙️  specify custom .env file path with { path: '/custom/path/.env' }\n(node:4) [MONGODB DRIVER] Warning: useNewUrlParser is a deprecated option: useNewUrlParser has no effect since Node.js Driver version 4.0.0 and will be removed in the next major version\n(Use `node --trace-warnings ...` to show where the warning was created)\n(node:4) [MONGODB DRIVER] Warning: useUnifiedTopology is a deprecated option: useUnifiedTopology has no effect since Node.js Driver version 4.0.0 and will be removed in the next major version\n[dotenv@17.2.2] injecting env (0) from .env -- tip: 📡 auto-backup env with Radar: https://dotenvx.com/radar\nConnected to MongoDB Atlas\nPathError [TypeError]: Missing parameter name at index 1: *; visit https://git.new/pathToRegexpError for info\n    at name (/var/task/backend/node_modules/path-to-regexp/dist/index.js:96:19)\n    at parse (/var/task/backend/node_modules/path-to-regexp/dist/index.js:113:68)\n    at pathToRegexp (/var/task/backend/node_modules/path-to-regexp/dist/index.js:267:58)\n    at Object.match (/var/task/backend/node_modules/path-to-regexp/dist/index.js:237:30)\n    at matcher (/var/task/backend/node_modules/router/lib/layer.js:86:23)\n    at new Layer (/var/task/backend/node_modules/router/lib/layer.js:93:62)\n    at Function.route (/var/task/backend/node_modules/router/index.js:428:17)\n    at Function.route (/var/task/backend/node_modules/express/lib/application.js:257:22)\n    at app.<computed> [as get] (/var/task/backend/node_modules/express/lib/application.js:478:22)\n    at Object.<anonymous> (/var/task/backend/server.js:124:9) {\n  originalPath: '*'\n}\nNode.js process exited with exit status: 1. The logs above can help with debugging the issue.","projectId":"prj_uRMIndd7p1kBQ5otSkgRpD3RLMnU","traceId":"","sessionId":"","invocationId":"01K9CSN4Z47J903XZGX5RD6GR1","instanceId":"","concurrency":-1},{"TimeUTC":"2025-11-06 14:38:17","timestampInMs":1762439897020,"requestPath":"multi-college-data-collection-system-9cwyx1q63.vercel.app/","requestMethod":"GET","requestQueryString":"","responseStatusCode":500,"requestId":"22fl2-1762439896833-13460c82ff12","requestUserAgent":"vercel-screenshot/1.0","level":"error","environment":"production","branch":"main","vercelCache":"","type":"lambda","function":"/server.js","host":"multi-college-data-collection-system-9cwyx1q63.vercel.app","deploymentDomain":"multi-college-data-collection-system-9cwyx1q63.vercel.app","deploymentId":"dpl_DXTZ13sYdb3DTyjZDb72UcQsc5rU","durationMs":1189,"region":"iad1","maxMemoryUsed":162,"memorySize":2048,"message":"","projectId":"prj_uRMIndd7p1kBQ5otSkgRpD3RLMnU","traceId":"","sessionId":"","invocationId":"01K9CSN7XWB00ZE26VB38YDZ81","instanceId":"","concurrency":1},{"TimeUTC":"2025-11-06 14:38:16","timestampInMs":1762439896711,"requestPath":"multi-college-data-collection-system-9cwyx1q63.vercel.app/","requestMethod":"GET","requestQueryString":"","responseStatusCode":-1,"requestId":"ntx6z-1762439893824-31b8d83b59c7","requestUserAgent":"vercel-screenshot/1.0","level":"error","environment":"production","branch":"main","vercelCache":"","type":"lambda","function":"/server.js","host":"multi-college-data-collection-system-9cwyx1q63.vercel.app","deploymentDomain":"multi-college-data-collection-system-9cwyx1q63.vercel.app","deploymentId":"dpl_DXTZ13sYdb3DTyjZDb72UcQsc5rU","durationMs":-1,"region":"iad1","maxMemoryUsed":-1,"memorySize":-1,"message":"[dotenv@17.2.2] injecting env (0) from .env -- tip: ⚙️  specify custom .env file path with { path: '/custom/path/.env' }\n(node:4) [MONGODB DRIVER] Warning: useNewUrlParser is a deprecated option: useNewUrlParser has no effect since Node.js Driver version 4.0.0 and will be removed in the next major version\n(Use `node --trace-warnings ...` to show where the warning was created)\n(node:4) [MONGODB DRIVER] Warning: useUnifiedTopology is a deprecated option: useUnifiedTopology has no effect since Node.js Driver version 4.0.0 and will be removed in the next major version\n[dotenv@17.2.2] injecting env (0) from .env -- tip: 🔐 prevent committing .env to code: https://dotenvx.com/precommit\nConnected to MongoDB Atlas\nPathError [TypeError]: Missing parameter name at index 1: *; visit https://git.new/pathToRegexpError for info\n    at name (/var/task/backend/node_modules/path-to-regexp/dist/index.js:96:19)\n    at parse (/var/task/backend/node_modules/path-to-regexp/dist/index.js:113:68)\n    at pathToRegexp (/var/task/backend/node_modules/path-to-regexp/dist/index.js:267:58)\n    at Object.match (/var/task/backend/node_modules/path-to-regexp/dist/index.js:237:30)\n    at matcher (/var/task/backend/node_modules/router/lib/layer.js:86:23)\n    at new Layer (/var/task/backend/node_modules/router/lib/layer.js:93:62)\n    at Function.route (/var/task/backend/node_modules/router/index.js:428:17)\n    at Function.route (/var/task/backend/node_modules/express/lib/application.js:257:22)\n    at app.<computed> [as get] (/var/task/backend/node_modules/express/lib/application.js:478:22)\n    at Object.<anonymous> (/var/task/backend/server.js:124:9) {\n  originalPath: '*'\n}\nNode.js process exited with exit status: 1. The logs above can help with debugging the issue.\n[dotenv@17.2.2] injecting env (0) from .env -- tip: ⚙️  specify custom .env file path with { path: '/custom/path/.env' }\n(node:4) [MONGODB DRIVER] Warning: useNewUrlParser is a deprecated option: useNewUrlParser has no effect since Node.js Driver version 4.0.0 and will be removed in the next major version\n(Use `node --trace-warnings ...` to show where the warning was created)\n(node:4) [MONGODB DRIVER] Warning: useUnifiedTopology is a deprecated option: useUnifiedTopology has no effect since Node.js Driver version 4.0.0 and will be removed in the next major version\n[dotenv@17.2.2] injecting env (0) from .env -- tip: 🔐 prevent committing .env to code: https://dotenvx.com/precommit\nConnected to MongoDB Atlas\nPathError [TypeError]: Missing parameter name at index 1: *; visit https://git.new/pathToRegexpError for info\n    at name (/var/task/backend/node_modules/path-to-regexp/dist/index.js:96:19)\n    at parse (/var/task/backend/node_modules/path-to-regexp/dist/index.js:113:68)\n    at pathToRegexp (/var/task/backend/node_modules/path-to-regexp/dist/index.js:267:58)\n    at Object.match (/var/task/backend/node_modules/path-to-regexp/dist/index.js:237:30)\n    at matcher (/var/task/backend/node_modules/router/lib/layer.js:86:23)\n    at new Layer (/var/task/backend/node_modules/router/lib/layer.js:93:62)\n    at Function.route (/var/task/backend/node_modules/router/index.js:428:17)\n    at Function.route (/var/task/backend/node_modules/express/lib/application.js:257:22)\n    at app.<computed> [as get] (/var/task/backend/node_modules/express/lib/application.js:478:22)\n    at Object.<anonymous> (/var/task/backend/server.js:124:9) {\n  originalPath: '*'\n}\nNode.js process exited with exit status: 1. The logs above can help with debugging the issue.","projectId":"prj_uRMIndd7p1kBQ5otSkgRpD3RLMnU","traceId":"","sessionId":"","invocationId":"01K9CSN4Z2J7858XPPWQD4C9KN","instanceId":"","concurrency":-1},{"TimeUTC":"2025-11-06 14:38:13","timestampInMs":1762439893987,"requestPath":"multi-college-data-collection-system-9cwyx1q63.vercel.app/","requestMethod":"GET","requestQueryString":"","responseStatusCode":500,"requestId":"jv7vr-1762439893705-4eaa8b5f58ab","requestUserAgent":"vercel-screenshot/1.0","level":"error","environment":"production","branch":"main","vercelCache":"","type":"lambda","function":"/server.js","host":"multi-college-data-collection-system-9cwyx1q63.vercel.app","deploymentDomain":"multi-college-data-collection-system-9cwyx1q63.vercel.app","deploymentId":"dpl_DXTZ13sYdb3DTyjZDb72UcQsc5rU","durationMs":1334,"region":"iad1","maxMemoryUsed":160,"memorySize":2048,"message":"","projectId":"prj_uRMIndd7p1kBQ5otSkgRpD3RLMnU","traceId":"","sessionId":"","invocationId":"01K9CSN4Z47J903XZGX5RD6GR1","instanceId":"","concurrency":1},{"TimeUTC":"2025-11-06 14:38:13","timestampInMs":1762439893986,"requestPath":"multi-college-data-collection-system-9cwyx1q63.vercel.app/","requestMethod":"GET","requestQueryString":"","responseStatusCode":500,"requestId":"ntx6z-1762439893824-31b8d83b59c7","requestUserAgent":"vercel-screenshot/1.0","level":"error","environment":"production","branch":"main","vercelCache":"","type":"lambda","function":"/server.js","host":"multi-college-data-collection-system-9cwyx1q63.vercel.app","deploymentDomain":"multi-college-data-collection-system-9cwyx1q63.vercel.app","deploymentId":"dpl_DXTZ13sYdb3DTyjZDb72UcQsc5rU","durationMs":1208,"region":"iad1","maxMemoryUsed":160,"memorySize":2048,"message":"","projectId":"prj_uRMIndd7p1kBQ5otSkgRpD3RLMnU","traceId":"","sessionId":"","invocationId":"01K9CSN4Z2J7858XPPWQD4C9KN","instanceId":"","concurrency":1}]